<?xml version="1.0" encoding="gb2312" ?><xml><row expect="17121085" opencode="05,03,10,07,04" specail="" opentime="2017-12-10 23:00:30"/><row expect="17121084" opencode="04,11,03,05,08" specail="" opentime="2017-12-10 22:50:30"/><row expect="17121083" opencode="02,06,11,01,09" specail="" opentime="2017-12-10 22:40:30"/><row expect="17121082" opencode="03,09,01,07,10" specail="" opentime="2017-12-10 22:30:30"/><row expect="17121081" opencode="06,11,05,03,02" specail="" opentime="2017-12-10 22:20:30"/><row expect="17121080" opencode="03,11,09,07,01" specail="" opentime="2017-12-10 22:10:30"/><row expect="17121079" opencode="08,01,06,11,03" specail="" opentime="2017-12-10 22:00:30"/><row expect="17121078" opencode="11,06,03,10,07" specail="" opentime="2017-12-10 21:50:30"/><row expect="17121077" opencode="03,10,07,04,09" specail="" opentime="2017-12-10 21:40:30"/><row expect="17121076" opencode="04,10,03,06,01" specail="" opentime="2017-12-10 21:30:30"/><row expect="17121075" opencode="08,03,05,01,06" specail="" opentime="2017-12-10 21:20:30"/><row expect="17121074" opencode="06,08,10,05,09" specail="" opentime="2017-12-10 21:10:30"/><row expect="17121073" opencode="08,04,07,11,01" specail="" opentime="2017-12-10 21:00:30"/><row expect="17121072" opencode="05,06,01,07,04" specail="" opentime="2017-12-10 20:50:30"/><row expect="17121071" opencode="03,04,08,06,11" specail="" opentime="2017-12-10 20:40:30"/><row expect="17121070" opencode="07,06,04,05,02" specail="" opentime="2017-12-10 20:30:30"/><row expect="17121069" opencode="11,07,06,01,03" specail="" opentime="2017-12-10 20:20:30"/><row expect="17121068" opencode="08,06,03,05,04" specail="" opentime="2017-12-10 20:10:30"/><row expect="17121067" opencode="05,11,02,01,07" specail="" opentime="2017-12-10 20:00:30"/><row expect="17121066" opencode="10,03,01,08,11" specail="" opentime="2017-12-10 19:50:30"/><row expect="17121065" opencode="02,11,09,04,10" specail="" opentime="2017-12-10 19:40:30"/><row expect="17121064" opencode="09,01,03,06,11" specail="" opentime="2017-12-10 19:30:30"/><row expect="17121063" opencode="08,03,10,05,06" specail="" opentime="2017-12-10 19:20:30"/><row expect="17121062" opencode="01,03,07,08,10" specail="" opentime="2017-12-10 19:10:30"/><row expect="17121061" opencode="03,01,08,07,10" specail="" opentime="2017-12-10 19:00:30"/><row expect="17121060" opencode="03,06,04,01,10" specail="" opentime="2017-12-10 18:50:30"/><row expect="17121059" opencode="11,09,04,03,08" specail="" opentime="2017-12-10 18:40:30"/><row expect="17121058" opencode="11,02,08,03,10" specail="" opentime="2017-12-10 18:30:30"/><row expect="17121057" opencode="11,09,01,10,04" specail="" opentime="2017-12-10 18:20:30"/><row expect="17121056" opencode="07,04,01,02,11" specail="" opentime="2017-12-10 18:10:30"/><row expect="17121055" opencode="03,02,06,07,05" specail="" opentime="2017-12-10 18:00:30"/><row expect="17121054" opencode="02,08,01,09,06" specail="" opentime="2017-12-10 17:50:30"/><row expect="17121053" opencode="11,05,01,03,08" specail="" opentime="2017-12-10 17:40:30"/><row expect="17121052" opencode="01,02,07,03,05" specail="" opentime="2017-12-10 17:30:30"/><row expect="17121051" opencode="04,08,03,01,11" specail="" opentime="2017-12-10 17:20:30"/><row expect="17121050" opencode="04,11,05,01,02" specail="" opentime="2017-12-10 17:10:30"/><row expect="17121049" opencode="01,04,11,08,05" specail="" opentime="2017-12-10 17:00:30"/><row expect="17121048" opencode="10,07,04,03,09" specail="" opentime="2017-12-10 16:50:30"/><row expect="17121047" opencode="10,05,11,07,08" specail="" opentime="2017-12-10 16:40:30"/><row expect="17121046" opencode="08,04,03,07,09" specail="" opentime="2017-12-10 16:30:30"/><row expect="17121045" opencode="04,02,05,03,09" specail="" opentime="2017-12-10 16:20:30"/><row expect="17121044" opencode="09,01,10,07,03" specail="" opentime="2017-12-10 16:10:30"/><row expect="17121043" opencode="02,03,04,10,01" specail="" opentime="2017-12-10 16:00:30"/><row expect="17121042" opencode="07,05,06,10,01" specail="" opentime="2017-12-10 15:50:30"/><row expect="17121041" opencode="04,09,05,01,07" specail="" opentime="2017-12-10 15:40:30"/><row expect="17121040" opencode="06,09,01,08,07" specail="" opentime="2017-12-10 15:30:30"/><row expect="17121039" opencode="05,02,08,07,09" specail="" opentime="2017-12-10 15:20:30"/><row expect="17121038" opencode="06,07,08,09,03" specail="" opentime="2017-12-10 15:10:30"/><row expect="17121037" opencode="03,01,07,10,02" specail="" opentime="2017-12-10 15:00:30"/><row expect="17121036" opencode="08,05,06,07,11" specail="" opentime="2017-12-10 14:50:30"/><row expect="17121035" opencode="07,03,06,11,04" specail="" opentime="2017-12-10 14:40:30"/><row expect="17121034" opencode="02,07,10,08,09" specail="" opentime="2017-12-10 14:30:30"/><row expect="17121033" opencode="11,03,05,06,08" specail="" opentime="2017-12-10 14:20:30"/><row expect="17121032" opencode="03,08,01,06,10" specail="" opentime="2017-12-10 14:10:30"/><row expect="17121031" opencode="04,11,09,07,08" specail="" opentime="2017-12-10 14:00:30"/><row expect="17121030" opencode="02,07,10,05,04" specail="" opentime="2017-12-10 13:50:30"/><row expect="17121029" opencode="09,07,05,11,06" specail="" opentime="2017-12-10 13:40:30"/><row expect="17121028" opencode="09,05,02,10,08" specail="" opentime="2017-12-10 13:30:30"/><row expect="17121027" opencode="07,04,10,09,03" specail="" opentime="2017-12-10 13:20:30"/><row expect="17121026" opencode="09,03,01,07,05" specail="" opentime="2017-12-10 13:10:30"/><row expect="17121025" opencode="08,04,10,07,05" specail="" opentime="2017-12-10 13:00:30"/><row expect="17121024" opencode="11,08,06,04,05" specail="" opentime="2017-12-10 12:50:30"/><row expect="17121023" opencode="08,02,06,01,04" specail="" opentime="2017-12-10 12:40:30"/><row expect="17121022" opencode="08,10,04,11,01" specail="" opentime="2017-12-10 12:30:30"/><row expect="17121021" opencode="09,03,04,07,11" specail="" opentime="2017-12-10 12:20:30"/><row expect="17121020" opencode="02,11,06,08,04" specail="" opentime="2017-12-10 12:10:30"/><row expect="17121019" opencode="10,04,01,05,02" specail="" opentime="2017-12-10 12:00:30"/><row expect="17121018" opencode="04,03,01,08,07" specail="" opentime="2017-12-10 11:50:30"/><row expect="17121017" opencode="11,05,06,08,01" specail="" opentime="2017-12-10 11:40:30"/><row expect="17121016" opencode="07,06,05,10,01" specail="" opentime="2017-12-10 11:30:30"/><row expect="17121015" opencode="09,07,03,04,08" specail="" opentime="2017-12-10 11:20:30"/><row expect="17121014" opencode="11,08,09,07,05" specail="" opentime="2017-12-10 11:10:30"/><row expect="17121013" opencode="11,06,08,01,09" specail="" opentime="2017-12-10 11:00:30"/><row expect="17121012" opencode="05,06,04,09,08" specail="" opentime="2017-12-10 10:50:30"/><row expect="17121011" opencode="09,02,10,11,06" specail="" opentime="2017-12-10 10:40:30"/><row expect="17121010" opencode="02,03,10,01,08" specail="" opentime="2017-12-10 10:30:30"/><row expect="17121009" opencode="02,05,04,10,07" specail="" opentime="2017-12-10 10:20:30"/><row expect="17121008" opencode="03,07,01,08,10" specail="" opentime="2017-12-10 10:10:30"/><row expect="17121007" opencode="01,09,07,10,04" specail="" opentime="2017-12-10 10:00:30"/><row expect="17121006" opencode="08,03,07,09,02" specail="" opentime="2017-12-10 09:50:30"/><row expect="17121005" opencode="09,02,01,05,03" specail="" opentime="2017-12-10 09:40:30"/><row expect="17121004" opencode="09,03,04,05,01" specail="" opentime="2017-12-10 09:30:30"/><row expect="17121003" opencode="01,11,05,04,03" specail="" opentime="2017-12-10 09:20:30"/><row expect="17121002" opencode="01,10,09,06,08" specail="" opentime="2017-12-10 09:10:30"/><row expect="17121001" opencode="02,08,06,09,10" specail="" opentime="2017-12-10 09:00:30"/></xml>