<?xml version="1.0" encoding="gb2312" ?><xml><row expect="17092885" opencode="04,11,01,05,09" specail="" opentime="2017-09-28 23:00:30"/><row expect="17092884" opencode="11,05,04,02,01" specail="" opentime="2017-09-28 22:50:30"/><row expect="17092883" opencode="11,10,01,07,06" specail="" opentime="2017-09-28 22:40:30"/><row expect="17092882" opencode="04,10,08,06,05" specail="" opentime="2017-09-28 22:30:30"/><row expect="17092881" opencode="06,08,03,09,01" specail="" opentime="2017-09-28 22:20:30"/><row expect="17092880" opencode="06,04,09,02,01" specail="" opentime="2017-09-28 22:10:30"/><row expect="17092879" opencode="06,03,07,04,01" specail="" opentime="2017-09-28 22:00:30"/><row expect="17092878" opencode="04,09,10,03,05" specail="" opentime="2017-09-28 21:50:30"/><row expect="17092877" opencode="03,06,05,11,04" specail="" opentime="2017-09-28 21:40:30"/><row expect="17092876" opencode="05,04,03,09,07" specail="" opentime="2017-09-28 21:30:30"/><row expect="17092875" opencode="08,01,06,04,09" specail="" opentime="2017-09-28 21:20:30"/><row expect="17092874" opencode="03,11,01,05,09" specail="" opentime="2017-09-28 21:10:30"/><row expect="17092873" opencode="09,11,08,10,03" specail="" opentime="2017-09-28 21:00:30"/><row expect="17092872" opencode="06,07,08,09,10" specail="" opentime="2017-09-28 20:50:30"/><row expect="17092871" opencode="03,05,01,06,02" specail="" opentime="2017-09-28 20:40:30"/><row expect="17092870" opencode="09,04,02,01,10" specail="" opentime="2017-09-28 20:30:30"/><row expect="17092869" opencode="08,07,04,01,05" specail="" opentime="2017-09-28 20:20:30"/><row expect="17092868" opencode="11,04,05,02,01" specail="" opentime="2017-09-28 20:10:30"/><row expect="17092867" opencode="07,03,08,02,11" specail="" opentime="2017-09-28 20:00:30"/><row expect="17092866" opencode="02,09,03,05,06" specail="" opentime="2017-09-28 19:50:30"/><row expect="17092865" opencode="10,01,02,07,09" specail="" opentime="2017-09-28 19:40:30"/><row expect="17092864" opencode="04,02,10,06,07" specail="" opentime="2017-09-28 19:30:30"/><row expect="17092863" opencode="01,09,02,11,07" specail="" opentime="2017-09-28 19:20:30"/><row expect="17092862" opencode="09,11,02,08,03" specail="" opentime="2017-09-28 19:10:30"/><row expect="17092861" opencode="03,06,05,11,01" specail="" opentime="2017-09-28 19:00:30"/><row expect="17092860" opencode="05,06,04,10,07" specail="" opentime="2017-09-28 18:50:30"/><row expect="17092859" opencode="06,08,02,01,03" specail="" opentime="2017-09-28 18:40:30"/><row expect="17092858" opencode="08,09,07,11,10" specail="" opentime="2017-09-28 18:30:30"/><row expect="17092857" opencode="09,03,11,01,04" specail="" opentime="2017-09-28 18:20:30"/><row expect="17092856" opencode="11,10,02,07,03" specail="" opentime="2017-09-28 18:10:30"/><row expect="17092855" opencode="10,04,05,06,01" specail="" opentime="2017-09-28 18:00:30"/><row expect="17092854" opencode="02,11,01,05,03" specail="" opentime="2017-09-28 17:50:30"/><row expect="17092853" opencode="04,03,01,10,06" specail="" opentime="2017-09-28 17:40:30"/><row expect="17092852" opencode="06,08,11,01,03" specail="" opentime="2017-09-28 17:30:30"/><row expect="17092851" opencode="06,11,07,04,03" specail="" opentime="2017-09-28 17:20:30"/><row expect="17092850" opencode="06,04,05,07,02" specail="" opentime="2017-09-28 17:10:30"/><row expect="17092849" opencode="07,02,08,11,10" specail="" opentime="2017-09-28 17:00:30"/><row expect="17092848" opencode="10,02,09,05,07" specail="" opentime="2017-09-28 16:50:30"/><row expect="17092847" opencode="11,04,01,03,06" specail="" opentime="2017-09-28 16:40:30"/><row expect="17092846" opencode="05,09,04,10,01" specail="" opentime="2017-09-28 16:30:30"/><row expect="17092845" opencode="03,09,01,06,02" specail="" opentime="2017-09-28 16:20:30"/><row expect="17092844" opencode="02,09,06,08,01" specail="" opentime="2017-09-28 16:10:30"/><row expect="17092843" opencode="05,01,10,04,02" specail="" opentime="2017-09-28 16:00:30"/><row expect="17092842" opencode="05,11,06,01,09" specail="" opentime="2017-09-28 15:50:30"/><row expect="17092841" opencode="03,08,05,02,07" specail="" opentime="2017-09-28 15:40:30"/><row expect="17092840" opencode="11,04,01,05,09" specail="" opentime="2017-09-28 15:30:30"/><row expect="17092839" opencode="05,04,07,06,09" specail="" opentime="2017-09-28 15:20:30"/><row expect="17092838" opencode="11,10,01,04,03" specail="" opentime="2017-09-28 15:10:30"/><row expect="17092837" opencode="07,03,09,06,02" specail="" opentime="2017-09-28 15:00:30"/><row expect="17092836" opencode="10,07,03,04,11" specail="" opentime="2017-09-28 14:50:30"/><row expect="17092835" opencode="05,09,03,06,01" specail="" opentime="2017-09-28 14:40:30"/><row expect="17092834" opencode="03,08,10,07,04" specail="" opentime="2017-09-28 14:30:30"/><row expect="17092833" opencode="11,05,09,06,10" specail="" opentime="2017-09-28 14:20:30"/><row expect="17092832" opencode="02,11,09,06,05" specail="" opentime="2017-09-28 14:10:30"/><row expect="17092831" opencode="08,05,06,01,11" specail="" opentime="2017-09-28 14:00:30"/><row expect="17092830" opencode="01,09,08,10,04" specail="" opentime="2017-09-28 13:50:30"/><row expect="17092829" opencode="11,03,07,02,04" specail="" opentime="2017-09-28 13:40:30"/><row expect="17092828" opencode="02,11,04,05,01" specail="" opentime="2017-09-28 13:30:30"/><row expect="17092827" opencode="05,04,09,10,08" specail="" opentime="2017-09-28 13:20:30"/><row expect="17092826" opencode="03,07,04,08,05" specail="" opentime="2017-09-28 13:10:30"/><row expect="17092825" opencode="11,06,10,07,03" specail="" opentime="2017-09-28 13:00:30"/><row expect="17092824" opencode="10,03,05,07,09" specail="" opentime="2017-09-28 12:50:30"/><row expect="17092823" opencode="07,10,11,02,05" specail="" opentime="2017-09-28 12:40:30"/><row expect="17092822" opencode="07,01,11,10,04" specail="" opentime="2017-09-28 12:30:30"/><row expect="17092821" opencode="01,10,04,09,05" specail="" opentime="2017-09-28 12:20:30"/><row expect="17092820" opencode="10,07,11,03,02" specail="" opentime="2017-09-28 12:10:30"/><row expect="17092819" opencode="09,11,06,01,03" specail="" opentime="2017-09-28 12:00:30"/><row expect="17092818" opencode="08,05,10,07,02" specail="" opentime="2017-09-28 11:50:30"/><row expect="17092817" opencode="07,10,11,02,09" specail="" opentime="2017-09-28 11:40:30"/><row expect="17092816" opencode="04,11,07,10,01" specail="" opentime="2017-09-28 11:30:30"/><row expect="17092815" opencode="06,08,05,02,04" specail="" opentime="2017-09-28 11:20:30"/><row expect="17092814" opencode="06,08,05,11,03" specail="" opentime="2017-09-28 11:10:30"/><row expect="17092813" opencode="11,04,06,02,10" specail="" opentime="2017-09-28 11:00:30"/><row expect="17092812" opencode="02,06,03,05,10" specail="" opentime="2017-09-28 10:50:30"/><row expect="17092811" opencode="11,02,08,09,04" specail="" opentime="2017-09-28 10:40:30"/><row expect="17092810" opencode="04,02,09,05,03" specail="" opentime="2017-09-28 10:30:30"/><row expect="17092809" opencode="07,10,02,03,11" specail="" opentime="2017-09-28 10:20:30"/><row expect="17092808" opencode="11,01,04,02,05" specail="" opentime="2017-09-28 10:10:30"/><row expect="17092807" opencode="09,01,08,11,07" specail="" opentime="2017-09-28 10:00:30"/><row expect="17092806" opencode="08,01,03,07,06" specail="" opentime="2017-09-28 09:50:30"/><row expect="17092805" opencode="11,10,04,09,08" specail="" opentime="2017-09-28 09:40:30"/><row expect="17092804" opencode="04,07,03,08,11" specail="" opentime="2017-09-28 09:30:30"/><row expect="17092803" opencode="09,04,02,05,10" specail="" opentime="2017-09-28 09:20:30"/><row expect="17092802" opencode="06,03,05,04,10" specail="" opentime="2017-09-28 09:10:30"/><row expect="17092801" opencode="05,07,11,02,04" specail="" opentime="2017-09-28 09:00:30"/></xml>