<?xml version="1.0" encoding="gb2312" ?><xml><row expect="17040785" opencode="08,01,06,11,02" specail="" opentime="2017-04-07 23:00:30"/><row expect="17040784" opencode="03,06,04,09,07" specail="" opentime="2017-04-07 22:50:30"/><row expect="17040783" opencode="04,02,03,01,08" specail="" opentime="2017-04-07 22:40:30"/><row expect="17040782" opencode="03,09,10,08,07" specail="" opentime="2017-04-07 22:30:30"/><row expect="17040781" opencode="05,02,04,10,03" specail="" opentime="2017-04-07 22:20:30"/><row expect="17040780" opencode="08,04,02,06,07" specail="" opentime="2017-04-07 22:10:30"/><row expect="17040779" opencode="08,04,10,03,11" specail="" opentime="2017-04-07 22:00:30"/><row expect="17040778" opencode="11,10,07,02,06" specail="" opentime="2017-04-07 21:50:30"/><row expect="17040777" opencode="01,03,11,10,04" specail="" opentime="2017-04-07 21:40:30"/><row expect="17040776" opencode="11,05,07,02,10" specail="" opentime="2017-04-07 21:30:30"/><row expect="17040775" opencode="02,08,01,05,07" specail="" opentime="2017-04-07 21:20:30"/><row expect="17040774" opencode="02,06,11,09,07" specail="" opentime="2017-04-07 21:10:30"/><row expect="17040773" opencode="08,11,01,02,09" specail="" opentime="2017-04-07 21:00:30"/><row expect="17040772" opencode="08,06,07,09,01" specail="" opentime="2017-04-07 20:50:30"/><row expect="17040771" opencode="07,11,09,03,05" specail="" opentime="2017-04-07 20:40:30"/><row expect="17040770" opencode="02,11,05,08,07" specail="" opentime="2017-04-07 20:30:30"/><row expect="17040769" opencode="06,08,03,05,07" specail="" opentime="2017-04-07 20:20:30"/><row expect="17040768" opencode="10,07,11,03,06" specail="" opentime="2017-04-07 20:10:30"/><row expect="17040767" opencode="09,01,02,11,07" specail="" opentime="2017-04-07 20:00:30"/><row expect="17040766" opencode="03,05,02,04,09" specail="" opentime="2017-04-07 19:50:30"/><row expect="17040765" opencode="11,10,06,04,02" specail="" opentime="2017-04-07 19:40:30"/><row expect="17040764" opencode="11,04,09,08,05" specail="" opentime="2017-04-07 19:30:30"/><row expect="17040763" opencode="06,05,10,07,04" specail="" opentime="2017-04-07 19:20:30"/><row expect="17040762" opencode="05,02,11,10,03" specail="" opentime="2017-04-07 19:10:30"/><row expect="17040761" opencode="02,05,10,04,06" specail="" opentime="2017-04-07 19:00:30"/><row expect="17040760" opencode="03,01,08,05,04" specail="" opentime="2017-04-07 18:50:30"/><row expect="17040759" opencode="06,05,04,09,11" specail="" opentime="2017-04-07 18:40:30"/><row expect="17040758" opencode="07,06,02,01,08" specail="" opentime="2017-04-07 18:30:30"/><row expect="17040757" opencode="11,10,05,02,07" specail="" opentime="2017-04-07 18:20:30"/><row expect="17040756" opencode="08,04,06,09,05" specail="" opentime="2017-04-07 18:10:30"/><row expect="17040755" opencode="08,07,10,09,04" specail="" opentime="2017-04-07 18:00:30"/><row expect="17040754" opencode="04,01,08,03,05" specail="" opentime="2017-04-07 17:50:30"/><row expect="17040753" opencode="07,05,10,09,11" specail="" opentime="2017-04-07 17:40:30"/><row expect="17040752" opencode="03,09,07,04,02" specail="" opentime="2017-04-07 17:30:30"/><row expect="17040751" opencode="08,07,11,03,05" specail="" opentime="2017-04-07 17:20:30"/><row expect="17040750" opencode="03,09,08,05,02" specail="" opentime="2017-04-07 17:10:30"/><row expect="17040749" opencode="01,05,02,03,06" specail="" opentime="2017-04-07 17:00:30"/><row expect="17040748" opencode="07,01,10,06,04" specail="" opentime="2017-04-07 16:50:30"/><row expect="17040747" opencode="02,11,03,06,10" specail="" opentime="2017-04-07 16:40:30"/><row expect="17040746" opencode="05,04,11,09,03" specail="" opentime="2017-04-07 16:30:30"/><row expect="17040745" opencode="04,02,08,05,06" specail="" opentime="2017-04-07 16:20:30"/><row expect="17040744" opencode="05,10,02,09,11" specail="" opentime="2017-04-07 16:10:30"/><row expect="17040743" opencode="05,03,09,10,08" specail="" opentime="2017-04-07 16:00:30"/><row expect="17040742" opencode="05,01,10,03,09" specail="" opentime="2017-04-07 15:50:30"/><row expect="17040741" opencode="07,04,10,01,05" specail="" opentime="2017-04-07 15:40:30"/><row expect="17040740" opencode="10,02,11,09,06" specail="" opentime="2017-04-07 15:30:30"/><row expect="17040739" opencode="01,10,11,03,08" specail="" opentime="2017-04-07 15:20:30"/><row expect="17040738" opencode="04,03,06,11,07" specail="" opentime="2017-04-07 15:10:30"/><row expect="17040737" opencode="09,01,08,02,03" specail="" opentime="2017-04-07 15:00:30"/><row expect="17040736" opencode="10,08,05,09,01" specail="" opentime="2017-04-07 14:50:30"/><row expect="17040735" opencode="01,04,07,08,11" specail="" opentime="2017-04-07 14:40:30"/><row expect="17040734" opencode="07,01,08,05,06" specail="" opentime="2017-04-07 14:30:30"/><row expect="17040733" opencode="06,10,07,05,04" specail="" opentime="2017-04-07 14:20:30"/><row expect="17040732" opencode="06,08,04,07,10" specail="" opentime="2017-04-07 14:10:30"/><row expect="17040731" opencode="02,05,01,10,09" specail="" opentime="2017-04-07 14:00:30"/><row expect="17040730" opencode="02,05,07,06,11" specail="" opentime="2017-04-07 13:50:30"/><row expect="17040729" opencode="11,06,02,08,09" specail="" opentime="2017-04-07 13:40:30"/><row expect="17040728" opencode="09,01,10,11,07" specail="" opentime="2017-04-07 13:30:30"/><row expect="17040727" opencode="07,08,03,10,09" specail="" opentime="2017-04-07 13:20:30"/><row expect="17040726" opencode="07,11,05,04,06" specail="" opentime="2017-04-07 13:10:30"/><row expect="17040725" opencode="02,07,01,06,08" specail="" opentime="2017-04-07 13:00:30"/><row expect="17040724" opencode="11,06,10,01,08" specail="" opentime="2017-04-07 12:50:30"/><row expect="17040723" opencode="08,06,07,01,02" specail="" opentime="2017-04-07 12:40:30"/><row expect="17040722" opencode="05,01,04,06,02" specail="" opentime="2017-04-07 12:30:30"/><row expect="17040721" opencode="10,06,11,02,08" specail="" opentime="2017-04-07 12:20:30"/><row expect="17040720" opencode="01,11,08,02,03" specail="" opentime="2017-04-07 12:10:30"/><row expect="17040719" opencode="04,11,07,02,08" specail="" opentime="2017-04-07 12:00:30"/><row expect="17040718" opencode="03,10,02,06,08" specail="" opentime="2017-04-07 11:50:30"/><row expect="17040717" opencode="06,05,07,10,03" specail="" opentime="2017-04-07 11:40:30"/><row expect="17040716" opencode="09,01,05,03,06" specail="" opentime="2017-04-07 11:30:30"/><row expect="17040715" opencode="01,06,11,04,08" specail="" opentime="2017-04-07 11:20:30"/><row expect="17040714" opencode="01,05,10,02,06" specail="" opentime="2017-04-07 11:10:30"/><row expect="17040713" opencode="08,06,04,10,05" specail="" opentime="2017-04-07 11:00:30"/><row expect="17040712" opencode="07,10,05,09,04" specail="" opentime="2017-04-07 10:50:30"/><row expect="17040711" opencode="05,06,10,09,04" specail="" opentime="2017-04-07 10:40:30"/><row expect="17040710" opencode="10,01,11,09,04" specail="" opentime="2017-04-07 10:30:30"/><row expect="17040709" opencode="01,07,05,03,09" specail="" opentime="2017-04-07 10:20:30"/><row expect="17040708" opencode="10,09,08,04,01" specail="" opentime="2017-04-07 10:10:30"/><row expect="17040707" opencode="08,05,09,01,06" specail="" opentime="2017-04-07 10:00:30"/><row expect="17040706" opencode="07,11,03,01,09" specail="" opentime="2017-04-07 09:50:30"/><row expect="17040705" opencode="05,06,08,02,01" specail="" opentime="2017-04-07 09:40:30"/><row expect="17040704" opencode="05,04,11,07,09" specail="" opentime="2017-04-07 09:30:30"/><row expect="17040703" opencode="11,03,05,06,01" specail="" opentime="2017-04-07 09:20:30"/><row expect="17040702" opencode="02,06,03,04,11" specail="" opentime="2017-04-07 09:10:30"/><row expect="17040701" opencode="05,08,07,10,11" specail="" opentime="2017-04-07 09:00:30"/></xml>