<?xml version="1.0" encoding="gb2312" ?><xml><row expect="17112485" opencode="09,05,07,06,04" specail="" opentime="2017-11-24 23:00:30"/><row expect="17112484" opencode="10,05,11,08,06" specail="" opentime="2017-11-24 22:50:30"/><row expect="17112483" opencode="07,09,03,01,04" specail="" opentime="2017-11-24 22:40:30"/><row expect="17112482" opencode="08,03,11,01,09" specail="" opentime="2017-11-24 22:30:30"/><row expect="17112481" opencode="08,04,03,05,01" specail="" opentime="2017-11-24 22:20:30"/><row expect="17112480" opencode="05,11,06,08,10" specail="" opentime="2017-11-24 22:10:30"/><row expect="17112479" opencode="07,05,01,04,09" specail="" opentime="2017-11-24 22:00:30"/><row expect="17112478" opencode="09,11,05,07,10" specail="" opentime="2017-11-24 21:50:30"/><row expect="17112477" opencode="01,07,09,06,03" specail="" opentime="2017-11-24 21:40:30"/><row expect="17112476" opencode="06,10,11,07,02" specail="" opentime="2017-11-24 21:30:30"/><row expect="17112475" opencode="01,09,02,04,03" specail="" opentime="2017-11-24 21:20:30"/><row expect="17112474" opencode="10,03,05,09,01" specail="" opentime="2017-11-24 21:10:30"/><row expect="17112473" opencode="11,02,10,09,04" specail="" opentime="2017-11-24 21:00:30"/><row expect="17112472" opencode="10,09,05,08,06" specail="" opentime="2017-11-24 20:50:30"/><row expect="17112471" opencode="07,03,01,11,05" specail="" opentime="2017-11-24 20:40:30"/><row expect="17112470" opencode="03,11,06,04,10" specail="" opentime="2017-11-24 20:30:30"/><row expect="17112469" opencode="06,08,07,04,09" specail="" opentime="2017-11-24 20:20:30"/><row expect="17112468" opencode="06,07,11,08,04" specail="" opentime="2017-11-24 20:10:30"/><row expect="17112467" opencode="01,08,07,10,04" specail="" opentime="2017-11-24 20:00:30"/><row expect="17112466" opencode="02,09,03,10,06" specail="" opentime="2017-11-24 19:50:30"/><row expect="17112465" opencode="06,08,05,01,09" specail="" opentime="2017-11-24 19:40:30"/><row expect="17112464" opencode="03,09,01,10,04" specail="" opentime="2017-11-24 19:30:30"/><row expect="17112463" opencode="02,01,07,06,04" specail="" opentime="2017-11-24 19:20:30"/><row expect="17112462" opencode="01,09,05,10,07" specail="" opentime="2017-11-24 19:10:30"/><row expect="17112461" opencode="02,06,03,11,05" specail="" opentime="2017-11-24 19:00:30"/><row expect="17112460" opencode="04,02,05,11,01" specail="" opentime="2017-11-24 18:50:30"/><row expect="17112459" opencode="04,10,11,06,01" specail="" opentime="2017-11-24 18:40:30"/><row expect="17112458" opencode="02,09,07,10,01" specail="" opentime="2017-11-24 18:30:30"/><row expect="17112457" opencode="06,05,04,11,07" specail="" opentime="2017-11-24 18:20:30"/><row expect="17112456" opencode="04,01,08,02,06" specail="" opentime="2017-11-24 18:10:30"/><row expect="17112455" opencode="04,11,08,05,07" specail="" opentime="2017-11-24 18:00:30"/><row expect="17112454" opencode="04,02,07,11,09" specail="" opentime="2017-11-24 17:50:30"/><row expect="17112453" opencode="02,08,05,06,09" specail="" opentime="2017-11-24 17:40:30"/><row expect="17112452" opencode="06,09,05,08,01" specail="" opentime="2017-11-24 17:30:30"/><row expect="17112451" opencode="05,08,10,03,06" specail="" opentime="2017-11-24 17:20:30"/><row expect="17112450" opencode="01,06,02,05,07" specail="" opentime="2017-11-24 17:10:30"/><row expect="17112449" opencode="10,01,08,06,09" specail="" opentime="2017-11-24 17:00:30"/><row expect="17112448" opencode="04,05,09,03,01" specail="" opentime="2017-11-24 16:50:30"/><row expect="17112447" opencode="03,09,11,08,07" specail="" opentime="2017-11-24 16:40:30"/><row expect="17112446" opencode="01,07,03,09,10" specail="" opentime="2017-11-24 16:30:30"/><row expect="17112445" opencode="06,01,10,02,04" specail="" opentime="2017-11-24 16:20:30"/><row expect="17112444" opencode="05,09,07,03,08" specail="" opentime="2017-11-24 16:10:30"/><row expect="17112443" opencode="01,04,02,09,11" specail="" opentime="2017-11-24 16:00:30"/><row expect="17112442" opencode="02,10,11,01,05" specail="" opentime="2017-11-24 15:50:30"/><row expect="17112441" opencode="09,10,06,07,02" specail="" opentime="2017-11-24 15:40:30"/><row expect="17112440" opencode="08,11,06,02,07" specail="" opentime="2017-11-24 15:30:30"/><row expect="17112439" opencode="01,06,03,04,08" specail="" opentime="2017-11-24 15:20:30"/><row expect="17112438" opencode="05,04,02,07,03" specail="" opentime="2017-11-24 15:10:30"/><row expect="17112437" opencode="01,05,09,04,02" specail="" opentime="2017-11-24 15:00:30"/><row expect="17112436" opencode="02,06,04,03,09" specail="" opentime="2017-11-24 14:50:30"/><row expect="17112435" opencode="03,05,07,11,09" specail="" opentime="2017-11-24 14:40:30"/><row expect="17112434" opencode="11,01,06,09,03" specail="" opentime="2017-11-24 14:30:30"/><row expect="17112433" opencode="03,05,01,02,04" specail="" opentime="2017-11-24 14:20:30"/><row expect="17112432" opencode="08,05,06,02,09" specail="" opentime="2017-11-24 14:10:30"/><row expect="17112431" opencode="04,01,06,05,07" specail="" opentime="2017-11-24 14:00:30"/><row expect="17112430" opencode="07,02,04,03,09" specail="" opentime="2017-11-24 13:50:30"/><row expect="17112429" opencode="11,09,08,03,05" specail="" opentime="2017-11-24 13:40:30"/><row expect="17112428" opencode="11,08,09,04,10" specail="" opentime="2017-11-24 13:30:30"/><row expect="17112427" opencode="02,11,06,08,01" specail="" opentime="2017-11-24 13:20:30"/><row expect="17112426" opencode="03,06,10,04,11" specail="" opentime="2017-11-24 13:10:30"/><row expect="17112425" opencode="04,10,01,08,03" specail="" opentime="2017-11-24 13:00:30"/><row expect="17112424" opencode="09,05,10,11,08" specail="" opentime="2017-11-24 12:50:30"/><row expect="17112423" opencode="05,07,02,10,04" specail="" opentime="2017-11-24 12:40:30"/><row expect="17112422" opencode="05,10,01,06,02" specail="" opentime="2017-11-24 12:30:30"/><row expect="17112421" opencode="05,07,11,04,03" specail="" opentime="2017-11-24 12:20:30"/><row expect="17112420" opencode="07,05,09,01,10" specail="" opentime="2017-11-24 12:10:30"/><row expect="17112419" opencode="06,07,02,10,03" specail="" opentime="2017-11-24 12:00:30"/><row expect="17112418" opencode="05,06,07,04,02" specail="" opentime="2017-11-24 11:50:30"/><row expect="17112417" opencode="07,06,04,01,05" specail="" opentime="2017-11-24 11:40:30"/><row expect="17112416" opencode="02,03,08,07,01" specail="" opentime="2017-11-24 11:30:30"/><row expect="17112415" opencode="09,06,05,04,08" specail="" opentime="2017-11-24 11:20:30"/><row expect="17112414" opencode="01,07,03,04,11" specail="" opentime="2017-11-24 11:10:30"/><row expect="17112413" opencode="09,10,03,02,06" specail="" opentime="2017-11-24 11:00:30"/><row expect="17112412" opencode="07,02,09,04,10" specail="" opentime="2017-11-24 10:50:30"/><row expect="17112411" opencode="04,08,05,06,10" specail="" opentime="2017-11-24 10:40:30"/><row expect="17112410" opencode="09,04,10,11,02" specail="" opentime="2017-11-24 10:30:30"/><row expect="17112409" opencode="04,03,01,06,10" specail="" opentime="2017-11-24 10:20:30"/><row expect="17112408" opencode="06,09,11,04,07" specail="" opentime="2017-11-24 10:10:30"/><row expect="17112407" opencode="01,10,03,11,09" specail="" opentime="2017-11-24 10:00:30"/><row expect="17112406" opencode="03,08,05,11,04" specail="" opentime="2017-11-24 09:50:30"/><row expect="17112405" opencode="10,07,11,08,02" specail="" opentime="2017-11-24 09:40:30"/><row expect="17112404" opencode="02,06,08,05,09" specail="" opentime="2017-11-24 09:30:30"/><row expect="17112403" opencode="03,11,09,07,10" specail="" opentime="2017-11-24 09:20:30"/><row expect="17112402" opencode="05,04,10,09,11" specail="" opentime="2017-11-24 09:10:30"/><row expect="17112401" opencode="05,07,06,10,01" specail="" opentime="2017-11-24 09:00:30"/></xml>