<?xml version="1.0" encoding="gb2312" ?><xml><row expect="18010685" opencode="07,04,10,01,05" specail="" opentime="2018-01-06 23:00:30"/><row expect="18010684" opencode="08,03,07,10,06" specail="" opentime="2018-01-06 22:50:30"/><row expect="18010683" opencode="06,10,09,07,04" specail="" opentime="2018-01-06 22:40:30"/><row expect="18010682" opencode="06,07,05,04,02" specail="" opentime="2018-01-06 22:30:30"/><row expect="18010681" opencode="10,06,04,01,09" specail="" opentime="2018-01-06 22:20:30"/><row expect="18010680" opencode="02,08,06,05,01" specail="" opentime="2018-01-06 22:10:30"/><row expect="18010679" opencode="02,11,03,01,09" specail="" opentime="2018-01-06 22:00:30"/><row expect="18010678" opencode="03,06,08,07,02" specail="" opentime="2018-01-06 21:50:30"/><row expect="18010677" opencode="03,01,07,05,02" specail="" opentime="2018-01-06 21:40:30"/><row expect="18010676" opencode="10,01,05,11,03" specail="" opentime="2018-01-06 21:30:30"/><row expect="18010675" opencode="04,05,02,11,09" specail="" opentime="2018-01-06 21:20:30"/><row expect="18010674" opencode="05,11,10,03,04" specail="" opentime="2018-01-06 21:10:30"/><row expect="18010673" opencode="10,07,04,08,03" specail="" opentime="2018-01-06 21:00:30"/><row expect="18010672" opencode="07,02,06,03,08" specail="" opentime="2018-01-06 20:50:30"/><row expect="18010671" opencode="09,02,08,03,11" specail="" opentime="2018-01-06 20:40:30"/><row expect="18010670" opencode="07,04,02,08,06" specail="" opentime="2018-01-06 20:30:30"/><row expect="18010669" opencode="07,03,10,05,08" specail="" opentime="2018-01-06 20:20:30"/><row expect="18010668" opencode="01,05,04,10,07" specail="" opentime="2018-01-06 20:10:30"/><row expect="18010667" opencode="10,09,05,07,11" specail="" opentime="2018-01-06 20:00:30"/><row expect="18010666" opencode="07,03,10,09,05" specail="" opentime="2018-01-06 19:50:30"/><row expect="18010665" opencode="02,11,05,04,06" specail="" opentime="2018-01-06 19:40:30"/><row expect="18010664" opencode="01,06,08,05,03" specail="" opentime="2018-01-06 19:30:30"/><row expect="18010663" opencode="11,02,10,01,06" specail="" opentime="2018-01-06 19:20:30"/><row expect="18010662" opencode="07,01,10,08,09" specail="" opentime="2018-01-06 19:10:30"/><row expect="18010661" opencode="03,07,05,09,08" specail="" opentime="2018-01-06 19:00:30"/><row expect="18010660" opencode="11,10,01,03,08" specail="" opentime="2018-01-06 18:50:30"/><row expect="18010659" opencode="07,10,03,06,08" specail="" opentime="2018-01-06 18:40:30"/><row expect="18010658" opencode="07,11,09,02,01" specail="" opentime="2018-01-06 18:30:30"/><row expect="18010657" opencode="07,10,02,09,04" specail="" opentime="2018-01-06 18:20:30"/><row expect="18010656" opencode="10,03,07,01,09" specail="" opentime="2018-01-06 18:10:30"/><row expect="18010655" opencode="01,05,10,08,04" specail="" opentime="2018-01-06 18:00:30"/><row expect="18010654" opencode="07,02,04,06,05" specail="" opentime="2018-01-06 17:50:30"/><row expect="18010653" opencode="07,06,08,03,02" specail="" opentime="2018-01-06 17:40:30"/><row expect="18010652" opencode="03,07,06,04,08" specail="" opentime="2018-01-06 17:30:30"/><row expect="18010651" opencode="05,02,07,10,01" specail="" opentime="2018-01-06 17:20:30"/><row expect="18010650" opencode="07,02,04,09,03" specail="" opentime="2018-01-06 17:10:30"/><row expect="18010649" opencode="08,02,10,09,01" specail="" opentime="2018-01-06 17:00:30"/><row expect="18010648" opencode="02,08,11,06,05" specail="" opentime="2018-01-06 16:50:30"/><row expect="18010647" opencode="06,11,05,03,08" specail="" opentime="2018-01-06 16:40:30"/><row expect="18010646" opencode="04,11,03,06,07" specail="" opentime="2018-01-06 16:30:30"/><row expect="18010645" opencode="09,10,08,05,06" specail="" opentime="2018-01-06 16:20:30"/><row expect="18010644" opencode="06,01,03,07,02" specail="" opentime="2018-01-06 16:10:30"/><row expect="18010643" opencode="11,02,08,07,05" specail="" opentime="2018-01-06 16:00:30"/><row expect="18010642" opencode="02,07,05,11,10" specail="" opentime="2018-01-06 15:50:30"/><row expect="18010641" opencode="03,05,01,04,11" specail="" opentime="2018-01-06 15:40:30"/><row expect="18010640" opencode="04,03,06,08,02" specail="" opentime="2018-01-06 15:30:30"/><row expect="18010639" opencode="03,05,08,07,02" specail="" opentime="2018-01-06 15:20:30"/><row expect="18010638" opencode="01,05,08,07,06" specail="" opentime="2018-01-06 15:10:30"/><row expect="18010637" opencode="06,04,03,02,09" specail="" opentime="2018-01-06 15:00:30"/><row expect="18010636" opencode="11,01,07,03,06" specail="" opentime="2018-01-06 14:50:30"/><row expect="18010635" opencode="06,09,01,04,05" specail="" opentime="2018-01-06 14:40:30"/><row expect="18010634" opencode="06,11,07,09,05" specail="" opentime="2018-01-06 14:30:30"/><row expect="18010633" opencode="06,04,01,08,05" specail="" opentime="2018-01-06 14:20:30"/><row expect="18010632" opencode="07,09,03,02,06" specail="" opentime="2018-01-06 14:10:30"/><row expect="18010631" opencode="05,04,02,11,07" specail="" opentime="2018-01-06 14:00:30"/><row expect="18010630" opencode="09,07,04,02,05" specail="" opentime="2018-01-06 13:50:30"/><row expect="18010629" opencode="03,06,04,10,11" specail="" opentime="2018-01-06 13:40:30"/><row expect="18010628" opencode="11,05,07,10,02" specail="" opentime="2018-01-06 13:30:30"/><row expect="18010627" opencode="04,11,09,08,10" specail="" opentime="2018-01-06 13:20:30"/><row expect="18010626" opencode="11,02,03,05,07" specail="" opentime="2018-01-06 13:10:30"/><row expect="18010625" opencode="09,04,08,01,05" specail="" opentime="2018-01-06 13:00:30"/><row expect="18010624" opencode="07,04,02,06,08" specail="" opentime="2018-01-06 12:50:30"/><row expect="18010623" opencode="04,07,06,11,01" specail="" opentime="2018-01-06 12:40:30"/><row expect="18010622" opencode="10,01,05,09,02" specail="" opentime="2018-01-06 12:30:30"/><row expect="18010621" opencode="08,07,06,11,01" specail="" opentime="2018-01-06 12:20:30"/><row expect="18010620" opencode="09,11,05,03,01" specail="" opentime="2018-01-06 12:10:30"/><row expect="18010619" opencode="05,04,01,08,11" specail="" opentime="2018-01-06 12:00:30"/><row expect="18010618" opencode="05,02,07,08,04" specail="" opentime="2018-01-06 11:50:30"/><row expect="18010617" opencode="09,04,07,10,05" specail="" opentime="2018-01-06 11:40:30"/><row expect="18010616" opencode="02,05,04,11,01" specail="" opentime="2018-01-06 11:30:30"/><row expect="18010615" opencode="06,01,09,04,10" specail="" opentime="2018-01-06 11:20:30"/><row expect="18010614" opencode="01,03,05,08,09" specail="" opentime="2018-01-06 11:10:30"/><row expect="18010613" opencode="05,01,04,03,09" specail="" opentime="2018-01-06 11:00:30"/><row expect="18010612" opencode="05,08,09,11,01" specail="" opentime="2018-01-06 10:50:30"/><row expect="18010611" opencode="11,06,10,02,09" specail="" opentime="2018-01-06 10:40:30"/><row expect="18010610" opencode="05,10,11,02,08" specail="" opentime="2018-01-06 10:30:30"/><row expect="18010609" opencode="09,04,01,02,11" specail="" opentime="2018-01-06 10:20:30"/><row expect="18010608" opencode="04,10,03,02,05" specail="" opentime="2018-01-06 10:10:30"/><row expect="18010607" opencode="07,05,08,03,02" specail="" opentime="2018-01-06 10:00:30"/><row expect="18010606" opencode="05,04,11,06,02" specail="" opentime="2018-01-06 09:50:30"/><row expect="18010605" opencode="02,10,07,06,03" specail="" opentime="2018-01-06 09:40:30"/><row expect="18010604" opencode="04,07,01,10,05" specail="" opentime="2018-01-06 09:30:30"/><row expect="18010603" opencode="07,05,02,09,01" specail="" opentime="2018-01-06 09:20:30"/><row expect="18010602" opencode="08,02,03,07,10" specail="" opentime="2018-01-06 09:10:30"/><row expect="18010601" opencode="04,02,09,10,03" specail="" opentime="2018-01-06 09:00:30"/></xml>