<?xml version="1.0" encoding="gb2312" ?><xml><row expect="15112179" opencode="06,04,02,10,08" opentime="2015-11-21 22:00:00"/><row expect="15112178" opencode="07,10,02,08,11" opentime="2015-11-21 21:50:00"/><row expect="15112177" opencode="10,11,05,06,07" opentime="2015-11-21 21:40:00"/><row expect="15112176" opencode="02,07,03,05,08" opentime="2015-11-21 21:30:00"/><row expect="15112175" opencode="11,03,08,04,01" opentime="2015-11-21 21:20:00"/><row expect="15112174" opencode="01,04,09,07,06" opentime="2015-11-21 21:10:00"/><row expect="15112173" opencode="04,08,02,05,01" opentime="2015-11-21 21:00:00"/><row expect="15112172" opencode="08,10,01,03,05" opentime="2015-11-21 20:50:00"/><row expect="15112171" opencode="02,09,03,05,06" opentime="2015-11-21 20:40:00"/><row expect="15112170" opencode="05,08,01,06,07" opentime="2015-11-21 20:30:00"/><row expect="15112169" opencode="04,02,08,09,06" opentime="2015-11-21 20:20:00"/><row expect="15112168" opencode="01,07,11,05,08" opentime="2015-11-21 20:10:00"/><row expect="15112167" opencode="10,07,11,02,03" opentime="2015-11-21 20:00:00"/><row expect="15112166" opencode="09,10,05,01,03" opentime="2015-11-21 19:50:00"/><row expect="15112165" opencode="02,05,03,10,09" opentime="2015-11-21 19:40:00"/><row expect="15112164" opencode="06,03,08,01,11" opentime="2015-11-21 19:30:00"/><row expect="15112163" opencode="05,01,11,02,10" opentime="2015-11-21 19:20:00"/><row expect="15112162" opencode="07,11,01,04,09" opentime="2015-11-21 19:10:00"/><row expect="15112161" opencode="03,05,06,09,04" opentime="2015-11-21 19:00:00"/><row expect="15112160" opencode="01,08,11,03,07" opentime="2015-11-21 18:50:00"/><row expect="15112159" opencode="01,02,11,10,04" opentime="2015-11-21 18:40:00"/><row expect="15112158" opencode="04,11,10,07,06" opentime="2015-11-21 18:30:00"/><row expect="15112157" opencode="02,10,07,03,09" opentime="2015-11-21 18:20:00"/><row expect="15112156" opencode="05,04,07,06,03" opentime="2015-11-21 18:10:00"/><row expect="15112155" opencode="07,05,01,04,08" opentime="2015-11-21 18:00:00"/><row expect="15112154" opencode="06,04,05,07,03" opentime="2015-11-21 17:50:00"/><row expect="15112153" opencode="01,11,08,09,02" opentime="2015-11-21 17:40:00"/><row expect="15112152" opencode="04,02,11,05,09" opentime="2015-11-21 17:30:00"/><row expect="15112151" opencode="07,03,10,09,05" opentime="2015-11-21 17:20:00"/><row expect="15112150" opencode="04,02,08,11,03" opentime="2015-11-21 17:10:00"/><row expect="15112149" opencode="04,09,08,05,10" opentime="2015-11-21 17:00:00"/><row expect="15112148" opencode="04,06,01,09,02" opentime="2015-11-21 16:50:00"/><row expect="15112147" opencode="07,02,04,01,11" opentime="2015-11-21 16:40:00"/><row expect="15112146" opencode="10,05,09,11,06" opentime="2015-11-21 16:30:00"/><row expect="15112145" opencode="11,06,08,07,03" opentime="2015-11-21 16:20:00"/><row expect="15112144" opencode="04,08,11,09,07" opentime="2015-11-21 16:10:00"/><row expect="15112143" opencode="05,04,11,06,02" opentime="2015-11-21 16:00:00"/><row expect="15112142" opencode="01,03,05,09,10" opentime="2015-11-21 15:50:00"/><row expect="15112141" opencode="04,11,06,02,10" opentime="2015-11-21 15:40:00"/><row expect="15112140" opencode="09,03,08,07,01" opentime="2015-11-21 15:30:00"/><row expect="15112139" opencode="11,04,02,09,10" opentime="2015-11-21 15:20:00"/><row expect="15112138" opencode="03,04,10,01,11" opentime="2015-11-21 15:10:00"/><row expect="15112137" opencode="11,04,03,07,02" opentime="2015-11-21 15:00:00"/><row expect="15112136" opencode="10,02,07,11,03" opentime="2015-11-21 14:50:00"/><row expect="15112135" opencode="04,07,02,06,10" opentime="2015-11-21 14:40:00"/><row expect="15112134" opencode="05,02,09,10,06" opentime="2015-11-21 14:30:00"/><row expect="15112133" opencode="08,09,05,07,02" opentime="2015-11-21 14:20:00"/><row expect="15112132" opencode="11,08,07,03,10" opentime="2015-11-21 14:10:00"/><row expect="15112131" opencode="03,11,02,10,05" opentime="2015-11-21 14:00:00"/><row expect="15112130" opencode="10,06,04,02,01" opentime="2015-11-21 13:50:00"/><row expect="15112129" opencode="02,07,09,04,08" opentime="2015-11-21 13:40:00"/><row expect="15112128" opencode="06,01,02,09,03" opentime="2015-11-21 13:30:00"/><row expect="15112127" opencode="09,03,11,01,04" opentime="2015-11-21 13:20:00"/><row expect="15112126" opencode="10,05,04,11,02" opentime="2015-11-21 13:10:00"/><row expect="15112125" opencode="08,03,07,01,10" opentime="2015-11-21 13:00:00"/><row expect="15112124" opencode="11,03,05,10,02" opentime="2015-11-21 12:50:00"/><row expect="15112123" opencode="06,02,08,07,11" opentime="2015-11-21 12:40:00"/><row expect="15112122" opencode="01,05,08,02,07" opentime="2015-11-21 12:30:00"/><row expect="15112121" opencode="08,11,01,06,03" opentime="2015-11-21 12:20:00"/><row expect="15112120" opencode="06,09,05,07,03" opentime="2015-11-21 12:10:00"/><row expect="15112119" opencode="06,10,04,09,03" opentime="2015-11-21 12:00:00"/><row expect="15112118" opencode="06,10,02,07,04" opentime="2015-11-21 11:50:00"/><row expect="15112117" opencode="02,04,11,06,03" opentime="2015-11-21 11:40:00"/><row expect="15112116" opencode="06,07,11,05,02" opentime="2015-11-21 11:30:00"/><row expect="15112115" opencode="01,11,03,06,07" opentime="2015-11-21 11:20:00"/><row expect="15112114" opencode="09,06,03,11,08" opentime="2015-11-21 11:10:00"/><row expect="15112113" opencode="02,08,09,03,10" opentime="2015-11-21 11:00:00"/><row expect="15112112" opencode="05,08,01,09,02" opentime="2015-11-21 10:50:00"/><row expect="15112111" opencode="10,11,01,08,07" opentime="2015-11-21 10:40:00"/><row expect="15112110" opencode="03,06,04,01,10" opentime="2015-11-21 10:30:00"/><row expect="15112109" opencode="05,11,09,03,08" opentime="2015-11-21 10:20:00"/><row expect="15112108" opencode="04,07,03,09,02" opentime="2015-11-21 10:10:00"/><row expect="15112107" opencode="02,11,01,06,09" opentime="2015-11-21 10:00:00"/><row expect="15112106" opencode="03,06,10,07,05" opentime="2015-11-21 09:50:00"/><row expect="15112105" opencode="11,08,07,10,02" opentime="2015-11-21 09:40:00"/><row expect="15112104" opencode="03,04,10,11,05" opentime="2015-11-21 09:30:00"/><row expect="15112103" opencode="02,08,05,10,04" opentime="2015-11-21 09:20:00"/><row expect="15112102" opencode="04,02,09,07,05" opentime="2015-11-21 09:10:00"/><row expect="15112101" opencode="10,02,07,03,09" opentime="2015-11-21 09:00:00"/></xml>