<?xml version="1.0" encoding="gb2312" ?><xml><row expect="16101084" opencode="02,08,01,07,06" opentime="2016-10-10 22:20:00"/><row expect="16101083" opencode="09,04,11,01,02" opentime="2016-10-10 22:10:00"/><row expect="16101082" opencode="01,06,02,10,11" opentime="2016-10-10 22:00:00"/><row expect="16101081" opencode="03,02,05,04,11" opentime="2016-10-10 21:50:00"/><row expect="16101080" opencode="03,09,07,05,11" opentime="2016-10-10 21:40:00"/><row expect="16101079" opencode="06,09,04,08,11" opentime="2016-10-10 21:30:00"/><row expect="16101078" opencode="05,04,06,03,10" opentime="2016-10-10 21:20:00"/><row expect="16101077" opencode="03,09,11,04,08" opentime="2016-10-10 21:10:00"/><row expect="16101076" opencode="06,02,04,03,05" opentime="2016-10-10 21:00:00"/><row expect="16101075" opencode="03,11,02,05,01" opentime="2016-10-10 20:50:00"/><row expect="16101074" opencode="01,10,02,08,05" opentime="2016-10-10 20:40:00"/><row expect="16101073" opencode="08,01,06,07,02" opentime="2016-10-10 20:30:00"/><row expect="16101072" opencode="02,05,08,11,10" opentime="2016-10-10 20:20:00"/><row expect="16101071" opencode="10,07,01,08,06" opentime="2016-10-10 20:10:00"/><row expect="16101070" opencode="09,08,10,04,05" opentime="2016-10-10 20:00:00"/><row expect="16101069" opencode="03,08,10,09,05" opentime="2016-10-10 19:50:00"/><row expect="16101068" opencode="04,09,11,06,07" opentime="2016-10-10 19:40:00"/><row expect="16101067" opencode="01,04,03,10,06" opentime="2016-10-10 19:30:00"/><row expect="16101066" opencode="06,04,09,02,11" opentime="2016-10-10 19:20:00"/><row expect="16101065" opencode="04,09,10,11,08" opentime="2016-10-10 19:10:00"/><row expect="16101064" opencode="01,09,03,02,04" opentime="2016-10-10 19:00:00"/><row expect="16101063" opencode="04,11,05,02,07" opentime="2016-10-10 18:50:00"/><row expect="16101062" opencode="09,10,02,06,04" opentime="2016-10-10 18:40:00"/><row expect="16101061" opencode="03,02,09,06,10" opentime="2016-10-10 18:30:00"/><row expect="16101060" opencode="01,06,04,09,08" opentime="2016-10-10 18:20:00"/><row expect="16101059" opencode="09,02,03,04,08" opentime="2016-10-10 18:10:00"/><row expect="16101058" opencode="01,02,09,03,07" opentime="2016-10-10 18:00:00"/><row expect="16101057" opencode="06,08,03,10,11" opentime="2016-10-10 17:50:00"/><row expect="16101056" opencode="11,07,09,10,08" opentime="2016-10-10 17:40:00"/><row expect="16101055" opencode="09,04,11,06,10" opentime="2016-10-10 17:30:00"/><row expect="16101054" opencode="11,06,07,10,09" opentime="2016-10-10 17:20:00"/><row expect="16101053" opencode="11,01,10,07,08" opentime="2016-10-10 17:10:00"/><row expect="16101052" opencode="08,05,11,09,04" opentime="2016-10-10 17:00:00"/><row expect="16101051" opencode="03,07,04,11,10" opentime="2016-10-10 16:50:00"/><row expect="16101050" opencode="10,07,01,02,06" opentime="2016-10-10 16:40:00"/><row expect="16101049" opencode="04,09,01,05,08" opentime="2016-10-10 16:30:00"/><row expect="16101048" opencode="04,10,08,06,02" opentime="2016-10-10 16:20:00"/><row expect="16101047" opencode="03,04,09,08,06" opentime="2016-10-10 16:10:00"/><row expect="16101046" opencode="06,08,11,10,09" opentime="2016-10-10 16:00:00"/><row expect="16101045" opencode="04,02,05,03,08" opentime="2016-10-10 15:50:00"/><row expect="16101044" opencode="04,03,02,06,11" opentime="2016-10-10 15:40:00"/><row expect="16101043" opencode="07,03,11,08,02" opentime="2016-10-10 15:30:00"/><row expect="16101042" opencode="05,04,03,10,01" opentime="2016-10-10 15:20:00"/><row expect="16101041" opencode="06,08,04,05,09" opentime="2016-10-10 15:10:00"/><row expect="16101040" opencode="07,03,05,11,10" opentime="2016-10-10 15:00:00"/><row expect="16101039" opencode="02,07,04,11,06" opentime="2016-10-10 14:50:00"/><row expect="16101038" opencode="11,01,05,08,06" opentime="2016-10-10 14:40:00"/><row expect="16101037" opencode="07,11,10,01,08" opentime="2016-10-10 14:30:00"/><row expect="16101036" opencode="01,09,11,10,03" opentime="2016-10-10 14:20:00"/><row expect="16101035" opencode="04,02,05,09,06" opentime="2016-10-10 14:10:00"/><row expect="16101034" opencode="06,11,02,07,10" opentime="2016-10-10 14:00:00"/><row expect="16101033" opencode="02,04,11,07,01" opentime="2016-10-10 13:50:00"/><row expect="16101032" opencode="01,07,04,10,06" opentime="2016-10-10 13:40:00"/><row expect="16101031" opencode="08,04,02,09,03" opentime="2016-10-10 13:30:00"/><row expect="16101030" opencode="03,09,01,11,02" opentime="2016-10-10 13:20:00"/><row expect="16101029" opencode="11,09,03,02,08" opentime="2016-10-10 13:10:00"/><row expect="16101028" opencode="06,03,10,11,02" opentime="2016-10-10 13:00:00"/><row expect="16101027" opencode="08,03,05,11,06" opentime="2016-10-10 12:50:00"/><row expect="16101026" opencode="01,05,09,08,06" opentime="2016-10-10 12:40:00"/><row expect="16101025" opencode="09,07,03,10,05" opentime="2016-10-10 12:30:00"/><row expect="16101024" opencode="06,10,03,05,07" opentime="2016-10-10 12:20:00"/><row expect="16101023" opencode="06,11,08,05,09" opentime="2016-10-10 12:10:00"/><row expect="16101022" opencode="06,05,01,03,04" opentime="2016-10-10 12:00:00"/><row expect="16101021" opencode="02,03,09,01,08" opentime="2016-10-10 11:50:00"/><row expect="16101020" opencode="04,03,10,06,02" opentime="2016-10-10 11:40:00"/><row expect="16101019" opencode="09,04,01,03,07" opentime="2016-10-10 11:30:00"/><row expect="16101018" opencode="06,09,05,01,07" opentime="2016-10-10 11:20:00"/><row expect="16101017" opencode="05,08,07,02,09" opentime="2016-10-10 11:10:00"/><row expect="16101016" opencode="07,04,05,02,03" opentime="2016-10-10 11:00:00"/><row expect="16101015" opencode="07,09,08,11,05" opentime="2016-10-10 10:50:00"/><row expect="16101014" opencode="11,07,09,05,10" opentime="2016-10-10 10:40:00"/><row expect="16101013" opencode="10,05,01,11,03" opentime="2016-10-10 10:30:00"/><row expect="16101012" opencode="10,11,06,09,01" opentime="2016-10-10 10:20:00"/><row expect="16101011" opencode="02,04,11,09,07" opentime="2016-10-10 10:10:00"/><row expect="16101010" opencode="11,01,08,06,05" opentime="2016-10-10 10:00:00"/><row expect="16101009" opencode="10,11,04,08,06" opentime="2016-10-10 09:50:00"/><row expect="16101008" opencode="06,05,11,04,10" opentime="2016-10-10 09:40:00"/><row expect="16101007" opencode="09,07,06,08,01" opentime="2016-10-10 09:30:00"/><row expect="16101006" opencode="02,04,10,05,01" opentime="2016-10-10 09:20:00"/><row expect="16101005" opencode="04,11,07,02,03" opentime="2016-10-10 09:10:00"/><row expect="16101004" opencode="10,01,08,03,04" opentime="2016-10-10 09:00:00"/><row expect="16101003" opencode="08,06,10,05,04" opentime="2016-10-10 08:50:00"/><row expect="16101002" opencode="06,10,11,01,03" opentime="2016-10-10 08:40:00"/><row expect="16101001" opencode="03,02,07,05,11" opentime="2016-10-10 08:30:00"/></xml>