<?xml version="1.0" encoding="gb2312" ?><xml><row expect="16010579" opencode="05,01,09,10,06" opentime="2016-01-05 22:00:00"/><row expect="16010578" opencode="02,11,03,10,06" opentime="2016-01-05 21:50:00"/><row expect="16010577" opencode="06,11,07,05,03" opentime="2016-01-05 21:40:00"/><row expect="16010576" opencode="05,04,03,06,09" opentime="2016-01-05 21:30:00"/><row expect="16010575" opencode="02,03,06,11,09" opentime="2016-01-05 21:20:00"/><row expect="16010574" opencode="04,07,09,11,08" opentime="2016-01-05 21:10:00"/><row expect="16010573" opencode="04,11,01,07,06" opentime="2016-01-05 21:00:00"/><row expect="16010572" opencode="06,04,05,11,10" opentime="2016-01-05 20:50:00"/><row expect="16010571" opencode="08,07,03,04,09" opentime="2016-01-05 20:40:00"/><row expect="16010570" opencode="01,09,11,02,10" opentime="2016-01-05 20:30:00"/><row expect="16010569" opencode="02,09,10,03,06" opentime="2016-01-05 20:20:00"/><row expect="16010568" opencode="03,07,02,01,08" opentime="2016-01-05 20:10:00"/><row expect="16010567" opencode="04,05,03,07,01" opentime="2016-01-05 20:00:00"/><row expect="16010566" opencode="05,01,07,03,06" opentime="2016-01-05 19:50:00"/><row expect="16010565" opencode="09,08,04,10,02" opentime="2016-01-05 19:40:00"/><row expect="16010564" opencode="11,04,10,08,05" opentime="2016-01-05 19:30:00"/><row expect="16010563" opencode="08,06,10,11,05" opentime="2016-01-05 19:20:00"/><row expect="16010562" opencode="01,11,07,04,02" opentime="2016-01-05 19:10:00"/><row expect="16010561" opencode="07,02,08,10,09" opentime="2016-01-05 19:00:00"/><row expect="16010560" opencode="04,07,08,11,03" opentime="2016-01-05 18:50:00"/><row expect="16010559" opencode="02,04,03,11,09" opentime="2016-01-05 18:40:00"/><row expect="16010558" opencode="05,01,06,09,07" opentime="2016-01-05 18:30:00"/><row expect="16010557" opencode="08,10,11,06,09" opentime="2016-01-05 18:20:00"/><row expect="16010556" opencode="04,08,05,11,09" opentime="2016-01-05 18:10:00"/><row expect="16010555" opencode="10,08,01,04,09" opentime="2016-01-05 18:00:00"/><row expect="16010554" opencode="01,10,11,04,02" opentime="2016-01-05 17:50:00"/><row expect="16010553" opencode="01,05,08,02,09" opentime="2016-01-05 17:40:00"/><row expect="16010552" opencode="02,10,04,07,11" opentime="2016-01-05 17:30:00"/><row expect="16010551" opencode="10,03,02,04,06" opentime="2016-01-05 17:20:00"/><row expect="16010550" opencode="07,05,06,11,01" opentime="2016-01-05 17:10:00"/><row expect="16010549" opencode="04,05,01,09,08" opentime="2016-01-05 17:00:00"/><row expect="16010548" opencode="04,07,01,09,08" opentime="2016-01-05 16:50:00"/><row expect="16010547" opencode="06,01,10,03,04" opentime="2016-01-05 16:40:00"/><row expect="16010546" opencode="02,07,06,08,05" opentime="2016-01-05 16:30:00"/><row expect="16010545" opencode="07,11,06,04,03" opentime="2016-01-05 16:20:00"/><row expect="16010544" opencode="08,03,10,02,06" opentime="2016-01-05 16:10:00"/><row expect="16010543" opencode="07,11,05,09,01" opentime="2016-01-05 16:00:00"/><row expect="16010542" opencode="01,06,07,11,08" opentime="2016-01-05 15:50:00"/><row expect="16010541" opencode="02,11,05,04,09" opentime="2016-01-05 15:40:00"/><row expect="16010540" opencode="04,08,01,05,06" opentime="2016-01-05 15:30:00"/><row expect="16010539" opencode="01,03,07,06,10" opentime="2016-01-05 15:20:00"/><row expect="16010538" opencode="10,05,01,04,06" opentime="2016-01-05 15:10:00"/><row expect="16010537" opencode="06,02,10,01,07" opentime="2016-01-05 15:00:00"/><row expect="16010536" opencode="05,02,03,08,06" opentime="2016-01-05 14:50:00"/><row expect="16010535" opencode="10,11,09,07,01" opentime="2016-01-05 14:40:00"/><row expect="16010534" opencode="03,05,08,11,06" opentime="2016-01-05 14:30:00"/><row expect="16010533" opencode="11,04,06,01,02" opentime="2016-01-05 14:20:00"/><row expect="16010532" opencode="02,10,07,08,03" opentime="2016-01-05 14:10:00"/><row expect="16010531" opencode="08,04,10,11,05" opentime="2016-01-05 14:00:00"/><row expect="16010530" opencode="06,08,09,07,03" opentime="2016-01-05 13:50:00"/><row expect="16010529" opencode="04,08,01,03,10" opentime="2016-01-05 13:40:00"/><row expect="16010528" opencode="10,08,09,01,11" opentime="2016-01-05 13:30:00"/><row expect="16010527" opencode="01,06,05,08,11" opentime="2016-01-05 13:20:00"/><row expect="16010526" opencode="09,10,03,07,01" opentime="2016-01-05 13:10:00"/><row expect="16010525" opencode="08,06,07,01,09" opentime="2016-01-05 13:00:00"/><row expect="16010524" opencode="07,02,11,05,06" opentime="2016-01-05 12:50:00"/><row expect="16010523" opencode="11,06,07,03,10" opentime="2016-01-05 12:40:00"/><row expect="16010522" opencode="03,09,05,10,02" opentime="2016-01-05 12:30:00"/><row expect="16010521" opencode="11,05,08,02,09" opentime="2016-01-05 12:20:00"/><row expect="16010520" opencode="08,11,10,05,06" opentime="2016-01-05 12:10:00"/><row expect="16010519" opencode="11,04,10,01,08" opentime="2016-01-05 12:00:00"/><row expect="16010518" opencode="05,08,03,10,06" opentime="2016-01-05 11:50:00"/><row expect="16010517" opencode="10,06,02,05,01" opentime="2016-01-05 11:40:00"/><row expect="16010516" opencode="11,07,06,08,01" opentime="2016-01-05 11:30:00"/><row expect="16010515" opencode="05,03,01,08,09" opentime="2016-01-05 11:20:00"/><row expect="16010514" opencode="11,10,06,09,05" opentime="2016-01-05 11:10:00"/><row expect="16010513" opencode="07,10,03,09,06" opentime="2016-01-05 11:00:00"/><row expect="16010512" opencode="10,01,03,02,07" opentime="2016-01-05 10:50:00"/><row expect="16010511" opencode="05,04,09,02,03" opentime="2016-01-05 10:40:00"/><row expect="16010510" opencode="08,05,10,02,07" opentime="2016-01-05 10:30:00"/><row expect="16010509" opencode="06,05,11,03,10" opentime="2016-01-05 10:20:00"/><row expect="16010508" opencode="05,07,09,03,08" opentime="2016-01-05 10:10:00"/><row expect="16010507" opencode="07,02,11,09,10" opentime="2016-01-05 10:00:00"/><row expect="16010506" opencode="05,08,10,07,01" opentime="2016-01-05 09:50:00"/><row expect="16010505" opencode="02,11,06,08,04" opentime="2016-01-05 09:40:00"/><row expect="16010504" opencode="02,03,10,11,06" opentime="2016-01-05 09:30:00"/><row expect="16010503" opencode="11,09,06,05,07" opentime="2016-01-05 09:20:00"/><row expect="16010502" opencode="01,04,03,08,10" opentime="2016-01-05 09:10:00"/><row expect="16010501" opencode="03,05,06,01,02" opentime="2016-01-05 09:00:00"/></xml>