<?xml version="1.0" encoding="gb2312" ?><xml><row expect="17032685" opencode="03,09,05,10,11" specail="" opentime="2017-03-26 22:30:00"/><row expect="17032684" opencode="01,06,08,02,04" specail="" opentime="2017-03-26 22:20:00"/><row expect="17032683" opencode="05,11,01,08,09" specail="" opentime="2017-03-26 22:10:00"/><row expect="17032682" opencode="01,07,09,10,02" specail="" opentime="2017-03-26 22:00:00"/><row expect="17032681" opencode="03,06,11,08,05" specail="" opentime="2017-03-26 21:50:00"/><row expect="17032680" opencode="11,07,05,01,02" specail="" opentime="2017-03-26 21:40:00"/><row expect="17032679" opencode="06,05,08,04,09" specail="" opentime="2017-03-26 21:30:00"/><row expect="17032678" opencode="08,03,04,09,02" specail="" opentime="2017-03-26 21:20:00"/><row expect="17032677" opencode="06,08,02,01,07" specail="" opentime="2017-03-26 21:10:00"/><row expect="17032676" opencode="05,08,03,02,09" specail="" opentime="2017-03-26 21:00:00"/><row expect="17032675" opencode="11,07,01,08,10" specail="" opentime="2017-03-26 20:50:00"/><row expect="17032674" opencode="05,08,06,02,10" specail="" opentime="2017-03-26 20:40:00"/><row expect="17032673" opencode="09,11,06,07,03" specail="" opentime="2017-03-26 20:30:00"/><row expect="17032672" opencode="04,07,03,06,05" specail="" opentime="2017-03-26 20:20:00"/><row expect="17032671" opencode="05,01,04,11,07" specail="" opentime="2017-03-26 20:10:00"/><row expect="17032670" opencode="09,05,08,06,10" specail="" opentime="2017-03-26 20:00:00"/><row expect="17032669" opencode="04,02,10,06,03" specail="" opentime="2017-03-26 19:50:00"/><row expect="17032668" opencode="10,04,06,02,08" specail="" opentime="2017-03-26 19:40:00"/><row expect="17032667" opencode="08,11,02,07,04" specail="" opentime="2017-03-26 19:30:00"/><row expect="17032666" opencode="03,01,10,07,02" specail="" opentime="2017-03-26 19:20:00"/><row expect="17032665" opencode="02,06,03,08,05" specail="" opentime="2017-03-26 19:10:00"/><row expect="17032664" opencode="07,09,01,08,06" specail="" opentime="2017-03-26 19:00:00"/><row expect="17032663" opencode="06,09,03,07,10" specail="" opentime="2017-03-26 18:50:00"/><row expect="17032662" opencode="06,05,08,03,09" specail="" opentime="2017-03-26 18:40:00"/><row expect="17032661" opencode="06,11,02,07,03" specail="" opentime="2017-03-26 18:30:00"/><row expect="17032660" opencode="07,10,03,09,11" specail="" opentime="2017-03-26 18:20:00"/><row expect="17032659" opencode="09,01,07,05,08" specail="" opentime="2017-03-26 18:10:00"/><row expect="17032658" opencode="11,04,03,01,08" specail="" opentime="2017-03-26 18:00:00"/><row expect="17032657" opencode="04,06,07,09,03" specail="" opentime="2017-03-26 17:50:00"/><row expect="17032656" opencode="05,03,10,08,02" specail="" opentime="2017-03-26 17:40:00"/><row expect="17032655" opencode="07,08,01,11,02" specail="" opentime="2017-03-26 17:30:00"/><row expect="17032654" opencode="05,03,09,06,08" specail="" opentime="2017-03-26 17:20:00"/><row expect="17032653" opencode="11,03,02,01,06" specail="" opentime="2017-03-26 17:10:00"/><row expect="17032652" opencode="10,05,08,03,09" specail="" opentime="2017-03-26 17:00:00"/><row expect="17032651" opencode="06,07,08,11,10" specail="" opentime="2017-03-26 16:50:00"/><row expect="17032650" opencode="05,02,08,07,06" specail="" opentime="2017-03-26 16:40:00"/><row expect="17032649" opencode="06,09,07,02,10" specail="" opentime="2017-03-26 16:30:00"/><row expect="17032648" opencode="05,03,06,07,09" specail="" opentime="2017-03-26 16:20:00"/><row expect="17032647" opencode="07,03,06,09,02" specail="" opentime="2017-03-26 16:10:00"/><row expect="17032646" opencode="09,05,06,02,11" specail="" opentime="2017-03-26 16:00:00"/><row expect="17032645" opencode="05,01,06,02,07" specail="" opentime="2017-03-26 15:50:00"/><row expect="17032644" opencode="03,08,01,02,05" specail="" opentime="2017-03-26 15:40:00"/><row expect="17032643" opencode="03,08,06,09,01" specail="" opentime="2017-03-26 15:30:00"/><row expect="17032642" opencode="10,07,04,02,06" specail="" opentime="2017-03-26 15:20:00"/><row expect="17032641" opencode="03,08,06,04,11" specail="" opentime="2017-03-26 15:10:00"/><row expect="17032640" opencode="05,11,04,01,07" specail="" opentime="2017-03-26 15:00:00"/><row expect="17032639" opencode="09,05,02,07,10" specail="" opentime="2017-03-26 14:50:00"/><row expect="17032638" opencode="03,08,10,09,04" specail="" opentime="2017-03-26 14:40:00"/><row expect="17032637" opencode="03,11,04,10,01" specail="" opentime="2017-03-26 14:30:00"/><row expect="17032636" opencode="02,03,10,09,05" specail="" opentime="2017-03-26 14:20:00"/><row expect="17032635" opencode="02,11,01,09,03" specail="" opentime="2017-03-26 14:10:00"/><row expect="17032634" opencode="04,07,06,09,11" specail="" opentime="2017-03-26 14:00:00"/><row expect="17032633" opencode="10,07,09,03,08" specail="" opentime="2017-03-26 13:50:00"/><row expect="17032632" opencode="08,11,02,09,06" specail="" opentime="2017-03-26 13:40:00"/><row expect="17032631" opencode="07,02,08,05,01" specail="" opentime="2017-03-26 13:30:00"/><row expect="17032630" opencode="08,01,04,09,06" specail="" opentime="2017-03-26 13:20:00"/><row expect="17032629" opencode="01,07,04,06,05" specail="" opentime="2017-03-26 13:10:00"/><row expect="17032628" opencode="11,07,06,04,08" specail="" opentime="2017-03-26 13:00:00"/><row expect="17032627" opencode="07,02,04,01,11" specail="" opentime="2017-03-26 12:50:00"/><row expect="17032626" opencode="06,05,10,01,11" specail="" opentime="2017-03-26 12:40:00"/><row expect="17032625" opencode="03,09,08,06,04" specail="" opentime="2017-03-26 12:30:00"/><row expect="17032624" opencode="07,03,02,08,05" specail="" opentime="2017-03-26 12:20:00"/><row expect="17032623" opencode="05,11,08,09,01" specail="" opentime="2017-03-26 12:10:00"/><row expect="17032622" opencode="05,01,08,06,02" specail="" opentime="2017-03-26 12:00:00"/><row expect="17032621" opencode="04,02,09,01,08" specail="" opentime="2017-03-26 11:50:00"/><row expect="17032620" opencode="05,04,09,10,06" specail="" opentime="2017-03-26 11:40:00"/><row expect="17032619" opencode="02,05,10,07,06" specail="" opentime="2017-03-26 11:30:00"/><row expect="17032618" opencode="04,01,02,06,09" specail="" opentime="2017-03-26 11:20:00"/><row expect="17032617" opencode="10,06,01,03,11" specail="" opentime="2017-03-26 11:10:00"/><row expect="17032616" opencode="01,09,03,06,02" specail="" opentime="2017-03-26 11:00:00"/><row expect="17032615" opencode="01,10,11,06,03" specail="" opentime="2017-03-26 10:50:00"/><row expect="17032614" opencode="01,06,09,04,03" specail="" opentime="2017-03-26 10:40:00"/><row expect="17032613" opencode="04,05,07,09,06" specail="" opentime="2017-03-26 10:30:00"/><row expect="17032612" opencode="04,10,03,11,08" specail="" opentime="2017-03-26 10:20:00"/><row expect="17032611" opencode="08,06,05,09,02" specail="" opentime="2017-03-26 10:10:00"/><row expect="17032610" opencode="03,10,05,07,04" specail="" opentime="2017-03-26 10:00:00"/><row expect="17032609" opencode="04,07,06,09,11" specail="" opentime="2017-03-26 09:50:00"/><row expect="17032608" opencode="01,09,02,10,03" specail="" opentime="2017-03-26 09:40:00"/><row expect="17032607" opencode="07,02,09,01,04" specail="" opentime="2017-03-26 09:30:00"/><row expect="17032606" opencode="05,09,03,11,04" specail="" opentime="2017-03-26 09:20:00"/><row expect="17032605" opencode="03,07,11,09,02" specail="" opentime="2017-03-26 09:10:00"/><row expect="17032604" opencode="07,08,10,05,04" specail="" opentime="2017-03-26 09:00:00"/><row expect="17032603" opencode="07,10,03,11,06" specail="" opentime="2017-03-26 08:50:00"/><row expect="17032602" opencode="03,07,11,10,05" specail="" opentime="2017-03-26 08:40:00"/><row expect="17032601" opencode="04,05,06,03,10" specail="" opentime="2017-03-26 08:30:00"/></xml>