<?xml version="1.0" encoding="gb2312" ?><xml><row expect="17021584" opencode="10,02,11,09,05" opentime="2017-02-15 22:20:00"/><row expect="17021583" opencode="01,09,08,11,04" opentime="2017-02-15 22:10:00"/><row expect="17021582" opencode="04,01,08,05,09" opentime="2017-02-15 22:00:00"/><row expect="17021581" opencode="11,05,07,10,01" opentime="2017-02-15 21:50:00"/><row expect="17021580" opencode="10,11,03,01,06" opentime="2017-02-15 21:40:00"/><row expect="17021579" opencode="08,10,04,09,01" opentime="2017-02-15 21:30:00"/><row expect="17021578" opencode="02,11,07,05,06" opentime="2017-02-15 21:20:00"/><row expect="17021577" opencode="11,05,09,07,10" opentime="2017-02-15 21:10:00"/><row expect="17021576" opencode="03,05,10,02,07" opentime="2017-02-15 21:00:00"/><row expect="17021575" opencode="04,06,01,07,02" opentime="2017-02-15 20:50:00"/><row expect="17021574" opencode="01,10,08,07,03" opentime="2017-02-15 20:40:00"/><row expect="17021573" opencode="03,08,07,06,01" opentime="2017-02-15 20:30:00"/><row expect="17021572" opencode="07,08,02,03,09" opentime="2017-02-15 20:20:00"/><row expect="17021571" opencode="07,03,01,04,11" opentime="2017-02-15 20:10:00"/><row expect="17021570" opencode="01,09,04,02,11" opentime="2017-02-15 20:00:00"/><row expect="17021569" opencode="05,02,09,11,04" opentime="2017-02-15 19:50:00"/><row expect="17021568" opencode="01,02,10,03,07" opentime="2017-02-15 19:40:00"/><row expect="17021567" opencode="05,01,11,06,07" opentime="2017-02-15 19:30:00"/><row expect="17021566" opencode="02,11,09,05,08" opentime="2017-02-15 19:20:00"/><row expect="17021565" opencode="08,03,01,07,10" opentime="2017-02-15 19:10:00"/><row expect="17021564" opencode="11,09,07,04,02" opentime="2017-02-15 19:00:00"/><row expect="17021563" opencode="07,09,05,11,03" opentime="2017-02-15 18:50:00"/><row expect="17021562" opencode="02,10,04,08,01" opentime="2017-02-15 18:40:00"/><row expect="17021561" opencode="06,02,11,09,04" opentime="2017-02-15 18:30:00"/><row expect="17021560" opencode="10,11,02,08,09" opentime="2017-02-15 18:20:00"/><row expect="17021559" opencode="08,02,04,05,06" opentime="2017-02-15 18:10:00"/><row expect="17021558" opencode="07,01,09,08,11" opentime="2017-02-15 18:00:00"/><row expect="17021557" opencode="10,06,02,07,08" opentime="2017-02-15 17:50:00"/><row expect="17021556" opencode="02,06,09,03,07" opentime="2017-02-15 17:40:00"/><row expect="17021555" opencode="09,02,07,11,03" opentime="2017-02-15 17:30:00"/><row expect="17021554" opencode="10,01,09,03,02" opentime="2017-02-15 17:20:00"/><row expect="17021553" opencode="10,07,04,01,02" opentime="2017-02-15 17:10:00"/><row expect="17021552" opencode="06,03,10,04,08" opentime="2017-02-15 17:00:00"/><row expect="17021551" opencode="08,06,10,03,05" opentime="2017-02-15 16:50:00"/><row expect="17021550" opencode="06,11,01,03,09" opentime="2017-02-15 16:40:00"/><row expect="17021549" opencode="11,05,10,07,06" opentime="2017-02-15 16:30:00"/><row expect="17021548" opencode="10,03,05,07,06" opentime="2017-02-15 16:20:00"/><row expect="17021547" opencode="05,01,11,02,08" opentime="2017-02-15 16:10:00"/><row expect="17021546" opencode="07,09,04,06,05" opentime="2017-02-15 16:00:00"/><row expect="17021545" opencode="07,10,08,02,01" opentime="2017-02-15 15:50:00"/><row expect="17021544" opencode="01,03,09,02,05" opentime="2017-02-15 15:40:00"/><row expect="17021543" opencode="10,05,07,11,02" opentime="2017-02-15 15:30:00"/><row expect="17021542" opencode="01,11,03,06,08" opentime="2017-02-15 15:20:00"/><row expect="17021541" opencode="07,11,02,01,08" opentime="2017-02-15 15:10:00"/><row expect="17021540" opencode="03,04,01,02,08" opentime="2017-02-15 15:00:00"/><row expect="17021539" opencode="11,07,08,05,03" opentime="2017-02-15 14:50:00"/><row expect="17021538" opencode="08,03,07,05,02" opentime="2017-02-15 14:40:00"/><row expect="17021537" opencode="08,04,03,06,10" opentime="2017-02-15 14:30:00"/><row expect="17021536" opencode="06,10,03,08,01" opentime="2017-02-15 14:20:00"/><row expect="17021535" opencode="10,02,03,04,06" opentime="2017-02-15 14:10:00"/><row expect="17021534" opencode="05,03,08,01,10" opentime="2017-02-15 14:00:00"/><row expect="17021533" opencode="05,04,03,01,11" opentime="2017-02-15 13:50:00"/><row expect="17021532" opencode="07,10,03,04,02" opentime="2017-02-15 13:40:00"/><row expect="17021531" opencode="04,10,03,05,01" opentime="2017-02-15 13:30:00"/><row expect="17021530" opencode="05,08,02,04,11" opentime="2017-02-15 13:20:00"/><row expect="17021529" opencode="09,10,05,11,06" opentime="2017-02-15 13:10:00"/><row expect="17021528" opencode="10,11,07,01,08" opentime="2017-02-15 13:00:00"/><row expect="17021527" opencode="02,08,11,09,04" opentime="2017-02-15 12:50:00"/><row expect="17021526" opencode="03,08,10,11,04" opentime="2017-02-15 12:40:00"/><row expect="17021525" opencode="05,08,04,02,10" opentime="2017-02-15 12:30:00"/><row expect="17021524" opencode="07,08,05,10,03" opentime="2017-02-15 12:20:00"/><row expect="17021523" opencode="08,06,07,10,05" opentime="2017-02-15 12:10:00"/><row expect="17021522" opencode="07,04,03,02,05" opentime="2017-02-15 12:00:00"/><row expect="17021521" opencode="06,11,05,09,07" opentime="2017-02-15 11:50:00"/><row expect="17021520" opencode="09,01,05,07,06" opentime="2017-02-15 11:40:00"/><row expect="17021519" opencode="04,02,05,07,08" opentime="2017-02-15 11:30:00"/><row expect="17021518" opencode="11,08,10,05,01" opentime="2017-02-15 11:20:00"/><row expect="17021517" opencode="07,09,11,06,01" opentime="2017-02-15 11:10:00"/><row expect="17021516" opencode="02,07,06,01,05" opentime="2017-02-15 11:00:00"/><row expect="17021515" opencode="01,07,03,02,11" opentime="2017-02-15 10:50:00"/><row expect="17021514" opencode="09,06,01,10,07" opentime="2017-02-15 10:40:00"/><row expect="17021513" opencode="07,09,03,11,05" opentime="2017-02-15 10:30:00"/><row expect="17021512" opencode="10,03,08,02,06" opentime="2017-02-15 10:20:00"/><row expect="17021511" opencode="08,09,03,10,01" opentime="2017-02-15 10:10:00"/><row expect="17021510" opencode="11,07,08,04,01" opentime="2017-02-15 10:00:00"/><row expect="17021509" opencode="05,04,03,10,06" opentime="2017-02-15 09:50:00"/><row expect="17021508" opencode="10,02,11,04,01" opentime="2017-02-15 09:40:00"/><row expect="17021507" opencode="04,08,11,10,07" opentime="2017-02-15 09:30:00"/><row expect="17021506" opencode="03,01,08,05,04" opentime="2017-02-15 09:20:00"/><row expect="17021505" opencode="08,06,02,01,07" opentime="2017-02-15 09:10:00"/><row expect="17021504" opencode="06,08,11,02,07" opentime="2017-02-15 09:00:00"/><row expect="17021503" opencode="10,11,05,01,07" opentime="2017-02-15 08:50:00"/><row expect="17021502" opencode="11,07,01,10,04" opentime="2017-02-15 08:40:00"/><row expect="17021501" opencode="10,03,02,11,08" opentime="2017-02-15 08:30:00"/></xml>