<?xml version="1.0" encoding="gb2312" ?><xml><row expect="17032085" opencode="05,10,01,11,02" specail="" opentime="2017-03-20 22:30:00"/><row expect="17032084" opencode="02,11,01,06,04" specail="" opentime="2017-03-20 22:20:00"/><row expect="17032083" opencode="01,09,10,08,03" specail="" opentime="2017-03-20 22:10:00"/><row expect="17032082" opencode="08,07,02,03,09" specail="" opentime="2017-03-20 22:00:00"/><row expect="17032081" opencode="04,03,09,06,10" specail="" opentime="2017-03-20 21:50:00"/><row expect="17032080" opencode="08,04,03,05,02" specail="" opentime="2017-03-20 21:40:00"/><row expect="17032079" opencode="02,10,11,05,01" specail="" opentime="2017-03-20 21:30:00"/><row expect="17032078" opencode="10,07,02,01,04" specail="" opentime="2017-03-20 21:20:00"/><row expect="17032077" opencode="07,06,10,08,11" specail="" opentime="2017-03-20 21:10:00"/><row expect="17032076" opencode="08,05,01,03,04" specail="" opentime="2017-03-20 21:00:00"/><row expect="17032075" opencode="04,09,07,05,02" specail="" opentime="2017-03-20 20:50:00"/><row expect="17032074" opencode="07,06,09,10,08" specail="" opentime="2017-03-20 20:40:00"/><row expect="17032073" opencode="11,07,03,04,02" specail="" opentime="2017-03-20 20:30:00"/><row expect="17032072" opencode="08,10,02,06,03" specail="" opentime="2017-03-20 20:20:00"/><row expect="17032071" opencode="09,06,08,04,05" specail="" opentime="2017-03-20 20:10:00"/><row expect="17032070" opencode="04,10,03,05,06" specail="" opentime="2017-03-20 20:00:00"/><row expect="17032069" opencode="07,09,08,10,02" specail="" opentime="2017-03-20 19:50:00"/><row expect="17032068" opencode="11,02,04,09,07" specail="" opentime="2017-03-20 19:40:00"/><row expect="17032067" opencode="01,09,07,10,08" specail="" opentime="2017-03-20 19:30:00"/><row expect="17032066" opencode="08,01,04,09,06" specail="" opentime="2017-03-20 19:20:00"/><row expect="17032065" opencode="06,03,07,01,02" specail="" opentime="2017-03-20 19:10:00"/><row expect="17032064" opencode="09,04,06,03,07" specail="" opentime="2017-03-20 19:00:00"/><row expect="17032063" opencode="04,02,11,06,03" specail="" opentime="2017-03-20 18:50:00"/><row expect="17032062" opencode="03,11,01,10,09" specail="" opentime="2017-03-20 18:40:00"/><row expect="17032061" opencode="01,11,10,04,09" specail="" opentime="2017-03-20 18:30:00"/><row expect="17032060" opencode="07,02,05,01,08" specail="" opentime="2017-03-20 18:20:00"/><row expect="17032059" opencode="06,08,11,09,01" specail="" opentime="2017-03-20 18:10:00"/><row expect="17032058" opencode="03,10,07,05,06" specail="" opentime="2017-03-20 18:00:00"/><row expect="17032057" opencode="09,02,03,08,11" specail="" opentime="2017-03-20 17:50:00"/><row expect="17032056" opencode="04,01,08,06,03" specail="" opentime="2017-03-20 17:40:00"/><row expect="17032055" opencode="09,07,06,01,11" specail="" opentime="2017-03-20 17:30:00"/><row expect="17032054" opencode="02,05,10,03,11" specail="" opentime="2017-03-20 17:20:00"/><row expect="17032053" opencode="09,07,03,02,06" specail="" opentime="2017-03-20 17:10:00"/><row expect="17032052" opencode="05,07,01,03,08" specail="" opentime="2017-03-20 17:00:00"/><row expect="17032051" opencode="09,01,11,02,04" specail="" opentime="2017-03-20 16:50:00"/><row expect="17032050" opencode="02,07,11,10,05" specail="" opentime="2017-03-20 16:40:00"/><row expect="17032049" opencode="04,02,01,05,09" specail="" opentime="2017-03-20 16:30:00"/><row expect="17032048" opencode="10,01,06,09,03" specail="" opentime="2017-03-20 16:20:00"/><row expect="17032047" opencode="07,05,04,06,11" specail="" opentime="2017-03-20 16:10:00"/><row expect="17032046" opencode="01,11,02,03,10" specail="" opentime="2017-03-20 16:00:00"/><row expect="17032045" opencode="03,05,02,07,08" specail="" opentime="2017-03-20 15:50:00"/><row expect="17032044" opencode="01,10,05,04,06" specail="" opentime="2017-03-20 15:40:00"/><row expect="17032043" opencode="01,06,03,11,02" specail="" opentime="2017-03-20 15:30:00"/><row expect="17032042" opencode="09,04,03,08,01" specail="" opentime="2017-03-20 15:20:00"/><row expect="17032041" opencode="01,05,07,03,06" specail="" opentime="2017-03-20 15:10:00"/><row expect="17032040" opencode="08,11,10,07,06" specail="" opentime="2017-03-20 15:00:00"/><row expect="17032039" opencode="02,10,04,08,05" specail="" opentime="2017-03-20 14:50:00"/><row expect="17032038" opencode="09,07,04,05,01" specail="" opentime="2017-03-20 14:40:00"/><row expect="17032037" opencode="11,06,09,01,05" specail="" opentime="2017-03-20 14:30:00"/><row expect="17032036" opencode="11,06,08,07,03" specail="" opentime="2017-03-20 14:20:00"/><row expect="17032035" opencode="09,07,05,04,01" specail="" opentime="2017-03-20 14:10:00"/><row expect="17032034" opencode="07,05,01,06,08" specail="" opentime="2017-03-20 14:00:00"/><row expect="17032033" opencode="06,07,09,01,02" specail="" opentime="2017-03-20 13:50:00"/><row expect="17032032" opencode="06,09,04,03,08" specail="" opentime="2017-03-20 13:40:00"/><row expect="17032031" opencode="01,10,07,05,11" specail="" opentime="2017-03-20 13:30:00"/><row expect="17032030" opencode="09,01,06,04,07" specail="" opentime="2017-03-20 13:20:00"/><row expect="17032029" opencode="03,07,09,11,05" specail="" opentime="2017-03-20 13:10:00"/><row expect="17032028" opencode="06,05,10,07,02" specail="" opentime="2017-03-20 13:00:00"/><row expect="17032027" opencode="08,02,10,07,05" specail="" opentime="2017-03-20 12:50:00"/><row expect="17032026" opencode="08,04,02,01,10" specail="" opentime="2017-03-20 12:40:00"/><row expect="17032025" opencode="06,07,03,08,11" specail="" opentime="2017-03-20 12:30:00"/><row expect="17032024" opencode="10,09,06,05,07" specail="" opentime="2017-03-20 12:20:00"/><row expect="17032023" opencode="11,05,07,02,08" specail="" opentime="2017-03-20 12:10:00"/><row expect="17032022" opencode="10,02,05,06,01" specail="" opentime="2017-03-20 12:00:00"/><row expect="17032021" opencode="11,02,03,08,10" specail="" opentime="2017-03-20 11:50:00"/><row expect="17032020" opencode="09,03,02,11,04" specail="" opentime="2017-03-20 11:40:00"/><row expect="17032019" opencode="05,04,09,11,03" specail="" opentime="2017-03-20 11:30:00"/><row expect="17032018" opencode="10,11,02,06,03" specail="" opentime="2017-03-20 11:20:00"/><row expect="17032017" opencode="03,06,08,04,02" specail="" opentime="2017-03-20 11:10:00"/><row expect="17032016" opencode="01,09,02,08,05" specail="" opentime="2017-03-20 11:00:00"/><row expect="17032015" opencode="03,05,08,01,11" specail="" opentime="2017-03-20 10:50:00"/><row expect="17032014" opencode="02,10,11,01,03" specail="" opentime="2017-03-20 10:40:00"/><row expect="17032013" opencode="05,06,07,02,04" specail="" opentime="2017-03-20 10:30:00"/><row expect="17032012" opencode="03,06,10,02,04" specail="" opentime="2017-03-20 10:20:00"/><row expect="17032011" opencode="08,01,09,03,10" specail="" opentime="2017-03-20 10:10:00"/><row expect="17032010" opencode="11,03,09,02,05" specail="" opentime="2017-03-20 10:00:00"/><row expect="17032009" opencode="09,10,04,05,01" specail="" opentime="2017-03-20 09:50:00"/><row expect="17032008" opencode="05,10,06,01,04" specail="" opentime="2017-03-20 09:40:00"/><row expect="17032007" opencode="01,02,07,06,11" specail="" opentime="2017-03-20 09:30:00"/><row expect="17032006" opencode="06,09,01,04,02" specail="" opentime="2017-03-20 09:20:00"/><row expect="17032005" opencode="09,01,03,07,02" specail="" opentime="2017-03-20 09:10:00"/><row expect="17032004" opencode="10,11,08,06,05" specail="" opentime="2017-03-20 09:00:00"/><row expect="17032003" opencode="08,04,05,06,10" specail="" opentime="2017-03-20 08:50:00"/><row expect="17032002" opencode="04,11,08,09,01" specail="" opentime="2017-03-20 08:40:00"/><row expect="17032001" opencode="02,03,10,11,01" specail="" opentime="2017-03-20 08:30:00"/></xml>