<?xml version="1.0" encoding="gb2312" ?><xml><row expect="171109-85" opencode="07,10,06,08,02" specail="" opentime="2017-11-09 22:30:00"/><row expect="171109-84" opencode="09,01,04,11,03" specail="" opentime="2017-11-09 22:20:00"/><row expect="171109-83" opencode="03,05,01,04,09" specail="" opentime="2017-11-09 22:10:00"/><row expect="171109-82" opencode="10,03,05,04,06" specail="" opentime="2017-11-09 22:00:00"/><row expect="171109-81" opencode="04,06,10,09,07" specail="" opentime="2017-11-09 21:50:00"/><row expect="171109-80" opencode="07,04,03,05,11" specail="" opentime="2017-11-09 21:40:00"/><row expect="171109-79" opencode="01,05,06,07,04" specail="" opentime="2017-11-09 21:30:00"/><row expect="171109-78" opencode="10,04,05,08,06" specail="" opentime="2017-11-09 21:20:00"/><row expect="171109-77" opencode="05,06,08,07,03" specail="" opentime="2017-11-09 21:10:00"/><row expect="171109-76" opencode="11,03,01,08,05" specail="" opentime="2017-11-09 21:00:00"/><row expect="171109-75" opencode="01,10,09,03,02" specail="" opentime="2017-11-09 20:50:00"/><row expect="171109-74" opencode="11,10,08,07,09" specail="" opentime="2017-11-09 20:40:00"/><row expect="171109-73" opencode="01,02,04,09,06" specail="" opentime="2017-11-09 20:30:00"/><row expect="171109-72" opencode="11,07,08,02,05" specail="" opentime="2017-11-09 20:20:00"/><row expect="171109-71" opencode="08,05,04,11,07" specail="" opentime="2017-11-09 20:10:00"/><row expect="171109-70" opencode="05,07,06,01,09" specail="" opentime="2017-11-09 20:00:00"/><row expect="171109-69" opencode="11,02,04,09,05" specail="" opentime="2017-11-09 19:50:00"/><row expect="171109-68" opencode="04,08,07,09,01" specail="" opentime="2017-11-09 19:40:00"/><row expect="171109-67" opencode="10,01,05,06,04" specail="" opentime="2017-11-09 19:30:00"/><row expect="171109-66" opencode="07,09,08,06,05" specail="" opentime="2017-11-09 19:20:00"/><row expect="171109-65" opencode="04,11,07,08,05" specail="" opentime="2017-11-09 19:10:00"/><row expect="171109-64" opencode="04,08,05,06,03" specail="" opentime="2017-11-09 19:00:00"/><row expect="171109-63" opencode="04,05,06,10,07" specail="" opentime="2017-11-09 18:50:00"/><row expect="171109-62" opencode="07,01,04,02,05" specail="" opentime="2017-11-09 18:40:00"/><row expect="171109-61" opencode="04,08,09,10,07" specail="" opentime="2017-11-09 18:30:00"/><row expect="171109-60" opencode="08,05,04,03,09" specail="" opentime="2017-11-09 18:20:00"/><row expect="171109-59" opencode="05,07,04,03,10" specail="" opentime="2017-11-09 18:10:00"/><row expect="171109-58" opencode="01,09,02,03,11" specail="" opentime="2017-11-09 18:00:00"/><row expect="171109-57" opencode="10,11,01,02,06" specail="" opentime="2017-11-09 17:50:00"/><row expect="171109-56" opencode="04,03,02,11,07" specail="" opentime="2017-11-09 17:40:00"/><row expect="171109-55" opencode="10,07,03,08,04" specail="" opentime="2017-11-09 17:30:00"/><row expect="171109-54" opencode="03,04,11,08,02" specail="" opentime="2017-11-09 17:20:00"/><row expect="171109-53" opencode="02,07,10,03,09" specail="" opentime="2017-11-09 17:10:00"/><row expect="171109-52" opencode="04,03,02,06,01" specail="" opentime="2017-11-09 17:00:00"/><row expect="171109-51" opencode="08,10,07,02,11" specail="" opentime="2017-11-09 16:50:00"/><row expect="171109-50" opencode="08,02,01,04,11" specail="" opentime="2017-11-09 16:40:00"/><row expect="171109-49" opencode="11,08,07,06,03" specail="" opentime="2017-11-09 16:30:00"/><row expect="171109-48" opencode="11,07,06,10,09" specail="" opentime="2017-11-09 16:20:00"/><row expect="171109-47" opencode="09,11,10,02,01" specail="" opentime="2017-11-09 16:10:00"/><row expect="171109-46" opencode="11,01,04,03,05" specail="" opentime="2017-11-09 16:00:00"/><row expect="171109-45" opencode="05,06,02,11,08" specail="" opentime="2017-11-09 15:50:00"/><row expect="171109-44" opencode="03,04,01,05,08" specail="" opentime="2017-11-09 15:40:00"/><row expect="171109-43" opencode="09,04,02,11,07" specail="" opentime="2017-11-09 15:30:00"/><row expect="171109-42" opencode="04,02,03,08,07" specail="" opentime="2017-11-09 15:20:00"/><row expect="171109-41" opencode="05,09,01,11,06" specail="" opentime="2017-11-09 15:10:00"/><row expect="171109-40" opencode="02,07,05,10,03" specail="" opentime="2017-11-09 15:00:00"/><row expect="171109-39" opencode="05,07,10,06,01" specail="" opentime="2017-11-09 14:50:00"/><row expect="171109-38" opencode="01,10,11,07,06" specail="" opentime="2017-11-09 14:40:00"/><row expect="171109-37" opencode="08,11,07,05,04" specail="" opentime="2017-11-09 14:30:00"/><row expect="171109-36" opencode="01,07,08,11,10" specail="" opentime="2017-11-09 14:20:00"/><row expect="171109-35" opencode="11,06,02,01,10" specail="" opentime="2017-11-09 14:10:00"/><row expect="171109-34" opencode="08,05,09,07,01" specail="" opentime="2017-11-09 14:00:00"/><row expect="171109-33" opencode="06,03,05,01,04" specail="" opentime="2017-11-09 13:50:00"/><row expect="171109-32" opencode="10,02,11,03,06" specail="" opentime="2017-11-09 13:40:00"/><row expect="171109-31" opencode="04,09,03,11,06" specail="" opentime="2017-11-09 13:30:00"/><row expect="171109-30" opencode="04,10,02,08,06" specail="" opentime="2017-11-09 13:20:00"/><row expect="171109-29" opencode="11,02,08,06,09" specail="" opentime="2017-11-09 13:10:00"/><row expect="171109-28" opencode="03,07,04,11,05" specail="" opentime="2017-11-09 13:00:00"/><row expect="171109-27" opencode="08,11,03,01,06" specail="" opentime="2017-11-09 12:50:00"/><row expect="171109-26" opencode="10,03,05,09,07" specail="" opentime="2017-11-09 12:40:00"/><row expect="171109-25" opencode="05,04,11,02,07" specail="" opentime="2017-11-09 12:30:00"/><row expect="171109-24" opencode="09,05,11,10,08" specail="" opentime="2017-11-09 12:20:00"/><row expect="171109-23" opencode="06,07,11,08,01" specail="" opentime="2017-11-09 12:10:00"/><row expect="171109-22" opencode="05,09,03,02,07" specail="" opentime="2017-11-09 12:00:00"/><row expect="171109-21" opencode="09,07,06,04,08" specail="" opentime="2017-11-09 11:50:00"/><row expect="171109-20" opencode="04,01,06,09,02" specail="" opentime="2017-11-09 11:40:00"/><row expect="171109-19" opencode="10,01,08,05,09" specail="" opentime="2017-11-09 11:30:00"/><row expect="171109-18" opencode="01,04,02,05,11" specail="" opentime="2017-11-09 11:20:00"/><row expect="171109-17" opencode="01,06,10,07,08" specail="" opentime="2017-11-09 11:10:00"/><row expect="171109-16" opencode="11,01,04,02,03" specail="" opentime="2017-11-09 11:00:00"/><row expect="171109-15" opencode="08,01,11,10,03" specail="" opentime="2017-11-09 10:50:00"/><row expect="171109-14" opencode="05,10,06,01,09" specail="" opentime="2017-11-09 10:40:00"/><row expect="171109-13" opencode="05,01,11,08,04" specail="" opentime="2017-11-09 10:30:00"/><row expect="171109-12" opencode="07,11,10,01,06" specail="" opentime="2017-11-09 10:20:00"/><row expect="171109-11" opencode="08,04,09,10,06" specail="" opentime="2017-11-09 10:10:00"/><row expect="171109-10" opencode="03,11,02,06,09" specail="" opentime="2017-11-09 10:00:00"/><row expect="171109-09" opencode="06,09,10,07,02" specail="" opentime="2017-11-09 09:50:00"/><row expect="171109-08" opencode="03,09,08,01,06" specail="" opentime="2017-11-09 09:40:00"/><row expect="171109-07" opencode="01,06,02,05,08" specail="" opentime="2017-11-09 09:30:00"/><row expect="171109-06" opencode="02,08,10,09,06" specail="" opentime="2017-11-09 09:20:00"/><row expect="171109-05" opencode="07,06,03,10,05" specail="" opentime="2017-11-09 09:10:00"/><row expect="171109-04" opencode="04,11,09,06,05" specail="" opentime="2017-11-09 09:00:00"/><row expect="171109-03" opencode="04,10,11,09,05" specail="" opentime="2017-11-09 08:50:00"/><row expect="171109-02" opencode="02,07,09,01,03" specail="" opentime="2017-11-09 08:40:00"/><row expect="171109-01" opencode="08,11,10,01,02" specail="" opentime="2017-11-09 08:30:00"/></xml>